Workbook
Name Slicer_Platform: #N/A
Name Slicer_State3: #N/A

Sheet Sales_Analysis.xlsx
A1: Order_ID | B1: Customer_ID | C1: Customer_Name | D1: Gender | E1: Age | F1: Platform | G1: Order_Date | H1: Delivery_Date | I1: State | J1: City | K1: Category | L1: Product_ID | M1: Product_Name | N1: Brand | O1: Quantity | P1: Cost_Price | Q1: Selling_Price | R1: Discount_% | S1: Sales | T1: Profit | U1: Payment_Method | V1: Delivery_Status | W1: Customer_Rating | X1: Warehouse | Y1: Salesperson
A2: ORD100000 | B2: CUST10000 | C2: Ashley Cox | D2: Female | E2: 35 | F2: Flipkart | G2: 45988 | H2: 46078 | I2: Maharashtra | J2: Mumbai | K2: Home | L2: P4053 | M2: Pressure Cooker | N2: Prestige | O2: 1 | P2: 17415 | Q2: 19836.65 | R2: 20 | S2: 15869.32 | T2: 2421.65 | U2: Debit Card | V2: Cancelled | W2: 1 | X2: Mumbai Hub | Y2: Robin Hodges
A3: ORD100001 | B3: CUST10001 | C3: Rebecca Everett | D3: Female | E3: 41 | F3: Flipkart | G3: 45843 | H3: 45577 | I3: Maharashtra | J3: Pune | K3: Grocery | L3: P3274 | M3: Sunflower Oil | N3: Fortune | O3: 4 | P3: 13107 | Q3: 17607.4 | R3: 10 | S3: 63386.64 | T3: 18001.6 | U3: UPI | V3: Cancelled | W3: 2 | X3: Pune Hub | Y3: Austin Mann
A4: ORD100002 | B4: CUST10002 | C4: Jacob Dalton | D4: Male | E4: 22 | F4: Flipkart | G4: 45879 | H4: 45906 | I4: Delhi | J4: New Delhi | K4: Grocery | L4: P1312 | M4: Sunflower Oil | N4: Fortune | O4: 1 | P4: 1905 | Q4: 2290.68 | R4: 15 | S4: 1947.08 | T4: 385.68 | U4: Debit Card | V4: Cancelled | W4: 4 | X4: New Delhi Hub | Y4: Andres Wright
A5: ORD100003 | B5: CUST10003 | C5: Diana Murphy DDS | D5: Male | E5: 59 | F5: Flipkart | G5: 45608 | H5: 45927 | I5: Telangana | J5: Hyderabad | K5: Beauty | L5: P3240 | M5: Face Wash | N5: Loreal | O5: 3 | P5: 10574 | Q5: 11718.4 | R5: 20 | S5: 28124.16 | T5: 3433.2 | U5: Debit Card | V5: Delivered | W5: 2 | X5: Hyderabad Hub | Y5: Eugene Martin
A6: ORD100004 | B6: CUST10004 | C6: Henry Rojas | D6: Female | E6: 55 | F6: Flipkart | G6: 45558 | H6: 45575 | I6: Karnataka | J6: Bengaluru | K6: Beauty | L6: P5574 | M6: Face Wash | N6: Loreal | O6: 5 | P6: 19031 | Q6: 27531.63 | R6: 15 | S6: 117009.43 | T6: 42503.15 | U6: Credit Card | V6: Delivered | W6: 4 | X6: Bengaluru Hub | Y6: Amy Contreras
A7: ORD100005 | B7: CUST10005 | C7: Morgan Robinson | D7: Male | E7: 48 | F7: Flipkart | G7: 46027 | H7: 45728 | I7: Tamil Nadu | J7: Chennai | K7: Grocery | L7: P3562 | M7: Sunflower Oil | N7: Fortune | O7: 4 | P7: 7382 | Q7: 9091.91 | R7: 5 | S7: 34549.26 | T7: 6839.64 | U7: UPI | V7: Delivered | W7: 1 | X7: Chennai Hub | Y7: Mckenzie Brady
A8: ORD100006 | B8: CUST10006 | C8: Robert Peterson | D8: Female | E8: 32 | F8: Amazon | G8: 45610 | H8: 46130 | I8: Telangana | J8: Hyderabad | K8: Electronics | L8: P2671 | M8: Galaxy S24 | N8: Samsung | O8: 2 | P8: 26006 | Q8: 29271.93 | R8: 0 | S8: 58543.86 | T8: 6531.86 | U8: Debit Card | V8: Cancelled | W8: 5 | X8: Hyderabad Hub | Y8: Michele Taylor
A9: ORD100007 | B9: CUST10007 | C9: Lindsey Brown | D9: Male | E9: 54 | F9: Flipkart | G9: 45708 | H9: 45634 | I9: Karnataka | J9: Bengaluru | K9: Beauty | L9: P3840 | M9: Face Wash | N9: Loreal | O9: 3 | P9: 9411 | Q9: 12520.75 | R9: 15 | S9: 31927.91 | T9: 9329.25 | U9: Debit Card | V9: Delivered | W9: 2 | X9: Bengaluru Hub | Y9: Christina Stevens
A10: ORD100008 | B10: CUST10008 | C10: Charlotte Gilbert | D10: Female | E10: 46 | F10: Flipkart | G10: 45611 | H10: 45792 | I10: Maharashtra | J10: Mumbai | K10: Grocery | L10: P5256 | M10: Sunflower Oil | N10: Fortune | O10: 3 | P10: 18006 | Q10: 20107.58 | R10: 10 | S10: 54290.47 | T10: 6304.74 | U10: Debit Card | V10: Cancelled | W10: 3 | X10: Mumbai Hub | Y10: Clifford Newton
A11: ORD100009 | B11: CUST10009 | C11: Rachel Garcia | D11: Male | E11: 32 | F11: Flipkart | G11: 46067 | H11: 45805 | I11: Karnataka | J11: Bengaluru | K11: Beauty | L11: P3816 | M11: Face Wash | N11: Loreal | O11: 2 | P11: 2839 | Q11: 3511.61 | R11: 20 | S11: 5618.58 | T11: 1345.22 | U11: Credit Card | V11: In Transit | W11: 4 | X11: Bengaluru Hub | Y11: Jerome Campbell
A12: ORD100010 | B12: CUST10010 | C12: Travis Keller | D12: Female | E12: 46 | F12: Amazon | G12: 46069 | H12: 45474 | I12: Delhi | J12: New Delhi | K12: Fashion | L12: P2051 | M12: Air Max Shoes | N12: Nike | O12: 5 | P12: 15167 | Q12: 19780.36 | R12: 5 | S12: 93956.71 | T12: 23066.8 | U12: UPI | V12: Delivered | W12: 1 | X12: New Delhi Hub | Y12: Anthony Day
A13: ORD100011 | B13: CUST10011 | C13: Joshua Thompson | D13: Female | E13: 19 | F13: Flipkart | G13: 45854 | H13: 45561 | I13: Telangana | J13: Hyderabad | K13: Fashion | L13: P5949 | M13: Air Max Shoes | N13: Nike | O13: 4 | P13: 12428 | Q13: 15530.69 | R13: 0 | S13: 62122.76 | T13: 12410.76 | U13: COD | V13: Delivered | W13: 3 | X13: Hyderabad Hub | Y13: Devin Johnson
... A38: ORD100036 | B38: CUST10036 | C38: Sheila Townsend | D38: Female | E38: 49 | F38: Flipkart | G38: 46181 | H38: 45658 | I38: Tamil Nadu | J38: Chennai | K38: Fashion | L38: P1779 | M38: Air Max Shoes | N38: Nike | O38: 1 | P38: 26287 | Q38: 37421.5 | R38: 20 | S38: 29937.2 | T38: 11134.5 | U38: Debit Card | V38: In Transit | W38: 5 | X38: Chennai Hub | Y38: Kenneth Jackson
A39: ORD100037 | B39: CUST10037 | C39: Garrett Arnold | D39: Male | E39: 36 | F39: Amazon | G39: 45787 | H39: 46061 | J39: Mumbai | K39: Grocery | L39: P2750 | M39: Sunflower Oil | N39: Fortune | O39: 1 | P39: 7793 | Q39: 10301.16 | R39: 0 | S39: 10301.16 | T39: 2508.16 | U39: COD | V39: Cancelled | W39: 4 | X39: Mumbai Hub | Y39: Jessica Lewis
A40: ORD100038 | B40: CUST10038 | C40: Louis Johnston | D40: Female | E40: 27 | F40: Flipkart | G40: 45902 | H40: 45763 | I40: Delhi | J40: New Delhi | K40: Electronics | L40: P5210 | M40: Galaxy S24 | N40: Samsung | O40: 4 | P40: 2289 | Q40: 3275.78 | R40: 5 | S40: 12447.96 | T40: 3947.12 | U40: Debit Card | V40: Delivered | W40: 3 | X40: New Delhi Hub | Y40: James Alexander
A41: ORD100039 | B41: CUST10039 | C41: Nicole Mckenzie | D41: Male | E41: 26 | F41: Flipkart | G41: 46037 | H41: 45476 | I41: Karnataka | J41: Bengaluru | K41: Beauty | L41: P7944 | M41: Face Wash | N41: Loreal | O41: 5 | P41: 7115 | Q41: 7914.96 | R41: 0 | S41: 39574.8 | T41: 3999.8 | U41: UPI | V41: In Transit | W41: 3 | X41: Bengaluru Hub | Y41: Sarah Robinson
A42: ORD100040 | B42: CUST10040 | C42: Alexis Richardson | D42: Female | E42: 58 | F42: Amazon | G42: 45876 | H42: 45975 | I42: Maharashtra | J42: Pune | K42: Electronics | L42: P7018 | M42: iPhone 15 | N42: Apple | O42: 2 | P42: 25274 | Q42: 36619.98 | R42: 15 | S42: 62253.97 | T42: 22691.96 | U42: Credit Card | V42: Returned | W42: 5 | X42: Pune Hub | Y42: Patricia Gardner
A43: ORD100041 | B43: CUST10041 | C43: Jennifer Edwards | D43: Female | E43: 21 | F43: Flipkart | G43: 45859 | H43: 45904 | I43: Telangana | J43: Hyderabad | K43: Fashion | L43: P4859 | M43: Air Max Shoes | N43: Nike | O43: 4 | P43: 18988 | Q43: 21837.44 | R43: 15 | S43: 74247.3 | T43: 11397.76 | U43: COD | V43: Delivered | W43: 5 | X43: Hyderabad Hub | Y43: Alexa Wiley
A44: ORD100042 | B44: CUST10042 | C44: Russell Monroe | D44: Female | E44: 37 | F44: Amazon | G44: 46027 | H44: 45597 | I44: Delhi | J44: New Delhi | K44: Home | L44: P5990 | M44: Pressure Cooker | N44: Prestige | O44: 4 | P44: 20396 | Q44: 26976.2 | R44: 0 | S44: 107904.8 | T44: 26320.8 | U44: Debit Card | V44: In Transit | W44: 4 | X44: New Delhi Hub | Y44: Dr. Brian Miller
A45: ORD100043 | B45: CUST10043 | C45: Sara Weaver | D45: Male | E45: 57 | F45: Flipkart | G45: 46129 | H45: 45929 | I45: Maharashtra | J45: Pune | K45: Electronics | L45: P5182 | M45: Galaxy S24 | N45: Samsung | O45: 3 | P45: 2760 | Q45: 3800.52 | R45: 0 | S45: 11401.56 | T45: 3121.56 | U45: COD | V45: Returned | W45: 3 | X45: Pune Hub | Y45: Charles Fitzgerald
A46: ORD100044 | B46: CUST10044 | C46: Eric Harris | D46: Male | E46: 55 | F46: Amazon | G46: 45924 | H46: 45940 | I46: Delhi | J46: New Delhi | K46: Electronics | L46: P6167 | M46: Galaxy S24 | N46: Samsung | O46: 4 | P46: 16611 | Q46: 18707.32 | R46: 5 | S46: 71087.82 | T46: 8385.28 | U46: UPI | V46: Cancelled | W46: 1 | X46: New Delhi Hub | Y46: Richard Schaefer
A47: ORD100045 | B47: CUST10045 | C47: Amanda Elliott | D47: Female | E47: 54 | F47: Flipkart | G47: 46093 | H47: 45902 | I47: Delhi | J47: New Delhi | K47: Electronics | L47: P7269 | M47: Galaxy S24 | N47: Samsung | O47: 3 | P47: 29223 | Q47: 38901.68 | R47: 5 | S47: 110869.79 | T47: 29036.04 | U47: COD | V47: Delivered | W47: 1 | X47: New Delhi Hub | Y47: Benjamin Mora
A48: ORD100046 | B48: CUST10046 | C48: Annette Payne | D48: Male | E48: 42 | F48: Flipkart | G48: 46144 | H48: 45907 | I48: maharashtra | J48: Chennai | K48: electronics | L48: P5807 | N48: Prestige | O48: 5 | P48: 20367 | Q48: 25753.96 | R48: 15 | S48: 109454.33 | T48: 26934.8 | U48: UPI | V48: Delivered | W48: 5 | X48: Chennai Hub | Y48: Nicole Torres
A49: ORD100047 | B49: CUST10047 | C49: Aaron Clark MD | D49: Female | E49: 57 | F49: Flipkart | G49: 45707 | H49: 46002 | I49: Delhi | J49: New Delhi | K49: electronics | L49: P5991 | M49: Face Wash | N49: Loreal | O49: 2 | P49: 5958 | Q49: 6718.88 | R49: 20 | S49: 10750.21 | T49: 1521.76 | U49: Debit Card | V49: Cancelled | W49: 3 | X49: New Delhi Hub | Y49: Marvin Floyd
A50: ORD100048 | B50: CUST10048 | C50: Daniel Nichols | D50: Male | E50: 18 | F50: Flipkart | G50: 45683 | H50: 46170 | I50: Maharashtra | J50: Pune | K50: Beauty | L50: P5731 | M50: Face Wash | N50: Loreal | O50: 5 | P50: 29365 | Q50: 38587.11 | R50: 10 | S50: 173641.99 | T50: 46110.55 | U50: Credit Card | V50: Delivered | W50: 2 | X50: Pune Hub | Y50: Andrea Wolfe
A51: ORD100049 | B51: CUST10049 | C51: Cody Singh | D51: Male | E51: 60 | F51: Amazon | G51: 45772 | H51: 45532 | I51: Telangana | J51: Hyderabad | K51: Electronics | L51: P2525 | M51: Galaxy S24 | N51: Samsung | O51: 1 | P51: 21589 | Q51: 26488.47 | R51: 10 | S51: 23839.62 | T51: 4899.47 | U51: Debit Card | V51: Cancelled | W51: 3 | X51: Hyderabad Hub | Y51: Vickie Turner
A52: ORD100050 | B52: CUST10050 | C52: Jennifer Welch | D52: Male | E52: 24 | F52: Amazon | G52: 45811 | H52: 45533 | J52: Chennai | K52: Electronics | L52: P2909 | N52: Apple | O52: 2 | P52: 20982 | Q52: 27502.55 | R52: 10 | S52: 49504.59 | T52: 13041.1 | U52: COD | V52: Delivered | W52: 2 | X52: Chennai Hub | Y52: Elizabeth Moore
A53: ORD100051 | B53: CUST10051 | C53: Dan Lewis | D53: Female | E53: 36 | F53: Flipkart | G53: 45997 | H53: 45503 | I53: Telangana | J53: Hyderabad | K53: Home | L53: P1231 | M53: Pressure Cooker | N53: Prestige | O53: 5 | P53: 15977 | Q53: 21699.83 | R53: 15 | S53: 92224.28 | T53: 28614.15 | U53: Credit Card | V53: In Transit | W53: 3 | X53: Hyderabad Hub | Y53: Veronica Mays
A54: ORD100052 | B54: CUST10052 | C54: Rachel Weber | D54: Male | E54: 57 | F54: Amazon | G54: 46139 | H54: 45760 | I54: Maharashtra | J54: Pune | K54: Fashion | L54: P4664 | M54: Air Max Shoes | N54: Nike | O54: 1 | P54: 28567 | Q54: 38920.04 | R54: 15 | S54: 33082.03 | T54: 10353.04 | U54: UPI | V54: Delivered | W54: 2 | X54: Pune Hub | Y54: Cynthia Schwartz
A55: ORD100053 | B55: CUST10053 | C55: Henry Graves | D55: Male | E55: 43 | F55: Amazon | G55: 46026 | H55: 45490 | I55: Tamil Nadu | J55: Chennai | K55: Grocery | L55: P3946 | M55: Sunflower Oil | N55: Fortune | O55: 5 | P55: 4075 | Q55: 5183.29 | R55: 0 | S55: 25916.45 | T55: 5541.45 | U55: Credit Card | V55: Returned | W55: 3 | X55: Chennai Hub | Y55: Pamela White MD
A56: ORD100054 | B56: CUST10054 | C56: Angela Owen | D56: Male | E56: 56 | F56: Amazon | G56: 45917 | H56: 45866 | I56: Maharashtra | J56: Pune | K56: Fashion | L56: P4171 | M56: Air Max Shoes | N56: Nike | O56: 3 | P56: 10999 | Q56: 13707.58 | R56: 10 | S56: 37010.47 | T56: 8125.74 | U56: UPI | V56: Returned | W56: 3 | X56: Pune Hub | Y56: Nancy Martinez
A57: ORD100055 | B57: CUST10055 | C57: Garrett Garcia | D57: Male | E57: 41 | F57: Flipkart | G57: 45795 | H57: 45638 | I57: Telangana | J57: Hyderabad | K57: Electronics | L57: P9891 | M57: iPhone 15 | N57: Apple | O57: 4 | P57: 29239 | Q57: 37702.11 | R57: 20 | S57: 120646.75 | T57: 33852.44 | U57: COD | V57: In Transit | W57: 3 | X57: Hyderabad Hub | Y57: Julie Brown
A58: ORD100056 | B58: CUST10056 | C58: Danielle Smith | D58: Female | E58: 30 | F58: Amazon | G58: 46039 | H58: 45587 | I58: Delhi | J58: New Delhi | K58: Grocery | L58: P7484 | M58: Sunflower Oil | N58: Fortune | O58: 4 | P58: 22526 | Q58: 25803.23 | R58: 0 | S58: 103212.92 | T58: 13108.92 | U58: Credit Card | V58: Delivered | W58: 5 | X58: New Delhi Hub | Y58: James Lynch
A59: ORD100057 | B59: CUST10057 | C59: Ana Willis | D59: Male | E59: 32 | F59: Amazon | G59: 45923 | H59: 46053 | I59: Delhi | J59: New Delhi | K59: Electronics | L59: P1584 | M59: Galaxy S24 | N59: Samsung | O59: 3 | P59: 20408 | Q59: 25911.99 | R59: 20 | S59: 62188.78 | T59: 16511.97 | U59: UPI | V59: Delivered | W59: 4 | X59: New Delhi Hub | Y59: Paul Sanchez
A60: ORD100058 | B60: CUST10058 | C60: Briana Nguyen | D60: Female | E60: 35 | F60: Flipkart | G60: 45925 | H60: 45601 | I60: Tamil Nadu | J60: Chennai | K60: Grocery | L60: P1067 | M60: Sunflower Oil | N60: Fortune | O60: 3 | P60: 15427 | Q60: 22409.45 | R60: 20 | S60: 53782.68 | T60: 20947.35 | U60: Credit Card | V60: Delivered | X60: Chennai Hub | Y60: Michaela Huffman
A61: ORD100059 | B61: CUST10059 | C61: Theresa Spence | D61: Female | E61: 39 | F61: Amazon | G61: 46017 | H61: 46156 | I61: Tamil Nadu | J61: Chennai | K61: Fashion | L61: P1165 | M61: Air Max Shoes | N61: Nike | O61: 4 | P61: 7700 | Q61: 10108.3 | R61: 5 | S61: 38411.54 | T61: 9633.2 | U61: Credit Card | V61: Cancelled | W61: 3 | X61: Chennai Hub | Y61: Jonathan Vasquez MD
A62: ORD100060 | B62: CUST10060 | C62: Ashley Mann | D62: Female | E62: 41 | F62: Flipkart | G62: 46158 | H62: 45785 | I62: Karnataka | J62: Bengaluru | K62: Electronics | L62: P3831 | M62: Galaxy S24 | N62: Samsung | O62: 2 | P62: 21776 | Q62: 32410.34 | R62: 0 | S62: 64820.68 | T62: 21268.68 | U62: COD | V62: Cancelled | W62: 1 | X62: Bengaluru Hub | Y62: James Wells
A63: ORD100061 | B63: CUST10061 | C63: Vincent Anderson | D63: Female | E63: 31 | F63: Amazon | G63: 46026 | H63: 45677 | I63: Telangana | J63: Hyderabad | K63: Electronics | L63: P3580 | M63: iPhone 15 | N63: Apple | O63: 1 | P63: 8685 | Q63: 9884.19 | R63: 0 | S63: 9884.19 | T63: 1199.19 | U63: Debit Card | V63: Cancelled | W63: 2 | X63: Hyderabad Hub | Y63: Mary Nichols
A64: ORD100062 | B64: CUST10062 | C64: Jennifer Simpson | D64: Female | E64: 36 | F64: Flipkart | G64: 45492 | H64: 45496 | I64: Karnataka | J64: Bengaluru | K64: Fashion | L64: P1951 | M64: Air Max Shoes | N64: Nike | O64: 2 | P64: 19331 | Q64: 25103.5 | R64: 10 | S64: 45186.3 | T64: 11545 | U64: UPI | V64: Cancelled | W64: 5 | X64: Bengaluru Hub | Y64: Melanie Garrett
A65: ORD100063 | B65: CUST10063 | C65: Jose Lopez | D65: Male | E65: 28 | F65: Flipkart | G65: 45969 | H65: 46162 | I65: Karnataka | J65: Bengaluru | K65: Grocery | L65: P2022 | M65: Sunflower Oil | N65: Fortune | O65: 2 | P65: 25100 | Q65: 35286.35 | R65: 10 | S65: 63515.43 | T65: 20372.7 | U65: Credit Card | V65: Cancelled | W65: 1 | X65: Bengaluru Hub | Y65: Ann Bailey
A66: ORD100064 | B66: CUST10064 | C66: Robert Matthews | D66: Female | E66: 29 | F66: Amazon | G66: 46178 | H66: 45508 | I66: Maharashtra | J66: Pune | K66: Electronics | L66: P9092 | M66: iPhone 15 | N66: Apple | O66: 1 | P66: 13089 | Q66: 18927.23 | R66: 20 | S66: 15141.78 | T66: 5838.23 | U66: Debit Card | V66: In Transit | W66: 2 | X66: Pune Hub | Y66: Rebekah Garcia
A67: ORD100065 | B67: CUST10065 | C67: Alexander Wilson | D67: Female | E67: 21 | F67: Amazon | G67: 45713 | H67: 46198 | I67: Tamil Nadu | J67: Chennai | K67: Fashion | L67: P8750 | M67: Air Max Shoes | N67: Nike | O67: 5 | P67: 18711 | Q67: 25930.21 | R67: 10 | S67: 116685.94 | T67: 36096.05 | U67: Credit Card | V67: Returned | W67: 2 | X67: Chennai Hub | Y67: Christopher Shields
A68: ORD100066 | B68: CUST10066 | C68: Denise Fleming | D68: Female | E68: 40 | F68: Flipkart | G68: 46093 | H68: 45993 | I68: Telangana | J68: Hyderabad | K68: Home | L68: P8235 | M68: Pressure Cooker | N68: Prestige | O68: 5 | P68: 9159 | Q68: 11357.18 | R68: 10 | S68: 51107.31 | T68: 10990.9 | U68: UPI | V68: Delivered | W68: 1 | X68: Hyderabad Hub | Y68: Scott Valencia
A69: ORD100067 | B69: CUST10067 | C69: Eric Ryan | D69: Male | E69: 52 | F69: Amazon | G69: 46111 | H69: 45849 | I69: Karnataka | J69: Bengaluru | K69: Grocery | L69: P9701 | M69: Sunflower Oil | N69: Fortune | O69: 5 | P69: 21598 | Q69: 26103.26 | R69: 10 | S69: 117464.67 | T69: 22526.3 | U69: UPI | V69: Returned | W69: 2 | X69: Bengaluru Hub | Y69: Chad Goodman
A70: ORD100068 | B70: CUST10068 | C70: Heather Hernandez | D70: Male | E70: 56 | F70: Amazon | G70: 45583 | H70: 46162 | I70: Tamil Nadu | J70: Chennai | K70: Electronics | L70: P8994 | M70: Galaxy S24 | N70: Samsung | O70: 5 | P70: 13795 | Q70: 15605.93 | R70: 5 | S70: 74128.17 | T70: 9054.65 | U70: Credit Card | V70: Returned | W70: 1 | X70: Chennai Hub | Y70: Charles Vargas
A71: ORD100069 | B71: CUST10069 | C71: Eric White | D71: Male | E71: 35 | F71: Flipkart | G71: 45817 | H71: 45626 | I71: Telangana | J71: Hyderabad | K71: Electronics | L71: P2551 | M71: Galaxy S24 | N71: Samsung | O71: 1 | P71: 6094 | Q71: 8955.07 | R71: 0 | S71: 8955.07 | T71: 2861.07 | U71: Credit Card | V71: Cancelled | W71: 3 | X71: Hyderabad Hub | Y71: Mary Mckinney
A72: ORD100070 | B72: CUST10070 | C72: Drew Sanders | D72: Female | E72: 20 | F72: Flipkart | G72: 45827 | H72: 45810 | I72: Delhi | J72: New Delhi | K72: Fashion | L72: P7926 | M72: Air Max Shoes | N72: Nike | O72: 3 | P72: 20595 | Q72: 27199.45 | R72: 15 | S72: 69358.6 | T72: 19813.35 | U72: Debit Card | V72: Returned | W72: 3 | X72: New Delhi Hub | Y72: Mark Harris
... A86: ORD100084 | B86: CUST10084 | C86: David Price | D86: Male | E86: 28 | F86: Flipkart | G86: 45476 | H86: 45524 | I86: Telangana | J86: Hyderabad | K86: Grocery | L86: P4591 | M86: Sunflower Oil | N86: Fortune | O86: 1 | P86: 4067 | Q86: 4600.77 | R86: 5 | S86: 4370.73 | T86: 533.77 | U86: Credit Card | V86: Cancelled | W86: 4 | X86: Hyderabad Hub | Y86: Dillon Walter
A87: ORD100085 | B87: CUST10085 | C87: Alicia Williams | D87: Male | E87: 30 | F87: Flipkart | G87: 45538 | H87: 45763 | J87: Hyderabad | K87: Electronics | L87: P4020 | M87: Galaxy S24 | N87: Samsung | O87: 1 | P87: 20204 | Q87: 25799.41 | R87: 20 | S87: 20639.53 | T87: 5595.41 | U87: COD | V87: In Transit | W87: 5 | X87: Hyderabad Hub | Y87: Charles Moore
A88: ORD100086 | B88: CUST10086 | C88: Scott Johnson | D88: Male | E88: 21 | F88: Amazon | G88: 45938 | H88: 45620 | I88: Maharashtra | J88: Mumbai | K88: electronics | L88: P7653 | M88: Pressure Cooker | N88: Prestige | O88: 5 | P88: 2935 | Q88: 4246.66 | R88: 20 | S88: 16986.64 | T88: 6558.3 | U88: Credit Card | V88: Returned | W88: 1 | X88: Mumbai Hub | Y88: Scott Woodard
A89: ORD100087 | B89: CUST10087 | C89: Martha Hayes MD | D89: Male | E89: 55 | F89: Amazon | G89: 45733 | H89: 45692 | I89: Telangana | J89: Hyderabad | K89: Home | L89: P9025 | M89: Pressure Cooker | N89: Prestige | O89: 2 | P89: 11628 | Q89: 16635.4 | R89: 0 | S89: 33270.8 | T89: 10014.8 | U89: Credit Card | V89: Returned | W89: 2 | X89: Hyderabad Hub | Y89: Tonya Stark
A90: ORD100088 | B90: CUST10088 | C90: James Douglas | D90: Female | E90: 38 | F90: Amazon | G90: 45599 | H90: 46161 | I90: Delhi | J90: New Delhi | K90: Fashion | L90: P6023 | M90: Air Max Shoes | N90: Nike | O90: 2 | P90: 4071 | Q90: 6016.91 | R90: 10 | S90: 10830.44 | T90: 3891.82 | U90: Debit Card | V90: Returned | W90: 3 | X90: New Delhi Hub | Y90: Christine Horn
A91: ORD100089 | B91: CUST10089 | C91: Jeremy Ballard | D91: Male | E91: 47 | F91: Amazon | G91: 45860 | H91: 45764 | I91: Karnataka | J91: Bengaluru | K91: Fashion | L91: P5208 | M91: Air Max Shoes | N91: Nike | O91: 4 | P91: 542 | Q91: 720.88 | R91: 5 | S91: 2739.34 | T91: 715.52 | U91: UPI | V91: Cancelled | W91: 2 | X91: Bengaluru Hub | Y91: Julie Grimes
A92: ORD100090 | B92: CUST10090 | C92: Roger Sutton | D92: Male | E92: 27 | F92: Amazon | G92: 46004 | H92: 45830 | J92: Chennai | K92: Fashion | L92: P4867 | M92: Air Max Shoes | N92: Nike | O92: 2 | P92: 27409 | Q92: 32832.8 | R92: 10 | S92: 59099.04 | T92: 10847.6 | U92: Credit Card | V92: Returned | W92: 2 | X92: Chennai Hub | Y92: Dale Wood
A93: ORD100091 | B93: CUST10091 | C93: Jessica Howard | D93: Female | E93: 59 | F93: Amazon | G93: 45832 | H93: 45820 | I93: Delhi | J93: New Delhi | K93: Beauty | L93: P6132 | M93: Face Wash | N93: Loreal | O93: 5 | P93: 15267 | Q93: 20602.59 | R93: 10 | S93: 92711.65 | T93: 26677.95 | U93: Debit Card | V93: In Transit | W93: 3 | X93: New Delhi Hub | Y93: Brianna Peterson
A94: ORD100092 | B94: CUST10092 | C94: Gabrielle Roth | D94: Male | E94: 32 | F94: Flipkart | G94: 45715 | H94: 45716 | I94: Delhi | J94: New Delhi | K94: Grocery | L94: P3129 | M94: Sunflower Oil | N94: Fortune | O94: 3 | P94: 23028 | Q94: 26051.42 | R94: 0 | S94: 78154.26 | T94: 9070.26 | U94: Credit Card | V94: Cancelled | W94: 1 | X94: New Delhi Hub | Y94: John Lewis
A95: ORD100093 | B95: CUST10093 | C95: Michael Riley | D95: Male | E95: 49 | F95: Amazon | G95: 45842 | H95: 46187 | I95: Karnataka | J95: Bengaluru | K95: Grocery | L95: P5747 | M95: Sunflower Oil | N95: Fortune | O95: 4 | P95: 9934 | Q95: 14830.92 | R95: 5 | S95: 56357.5 | T95: 19587.68 | U95: UPI | V95: Cancelled | W95: 4 | X95: Bengaluru Hub | Y95: Ronald Phillips
A96: ORD100094 | B96: CUST10094 | C96: Ryan Stevens | D96: Female | E96: 36 | F96: Amazon | G96: 45748 | H96: 45653 | I96: maharashtra | J96: Chennai | K96: Beauty | L96: P5748 | M96: Face Wash | N96: Loreal | O96: 3 | P96: 28202 | Q96: 33957.63 | R96: 20 | S96: 81498.31 | T96: 17266.89 | U96: Credit Card | V96: Returned | W96: 2 | X96: Chennai Hub | Y96: Carrie Hamilton
A97: ORD100095 | B97: CUST10095 | C97: Denise Johnston | D97: Male | E97: 38 | F97: Amazon | G97: 45788 | H97: 45646 | I97: Tamil Nadu | J97: Chennai | K97: Electronics | L97: P4934 | M97: Galaxy S24 | N97: Samsung | O97: 1 | P97: 11734 | Q97: 14545.73 | R97: 15 | S97: 12363.87 | T97: 2811.73 | U97: Credit Card | V97: In Transit | W97: 1 | X97: Chennai Hub | Y97: Melissa Clark
A98: ORD100096 | B98: CUST10096 | C98: Helen Davis | D98: Female | E98: 32 | F98: Amazon | G98: 45524 | H98: 45927 | I98: Maharashtra | J98: Pune | K98: Electronics | L98: P4337 | M98: Galaxy S24 | N98: Samsung | O98: 3 | P98: 24769 | Q98: 27491.34 | R98: 0 | S98: 82474.02 | T98: 8167.02 | U98: Credit Card | V98: Returned | W98: 5 | X98: Pune Hub | Y98: Raven Howell
A99: ORD100097 | B99: CUST10097 | C99: William Gonzales | D99: Male | E99: 32 | F99: Amazon | G99: 45504 | H99: 46069 | I99: Delhi | J99: New Delhi | K99: Beauty | L99: P2438 | M99: Face Wash | N99: Loreal | O99: 1 | P99: 2439 | Q99: 3175.54 | R99: 5 | S99: 3016.76 | T99: 736.54 | U99: Credit Card | V99: Returned | W99: 3 | X99: New Delhi Hub | Y99: Shannon Miller
A100: ORD100098 | B100: CUST10098 | C100: Thomas Stewart | D100: Female | E100: 50 | F100: Amazon | G100: 45898 | H100: 45843 | I100: Tamil Nadu | J100: Chennai | K100: Beauty | L100: P6405 | M100: Face Wash | N100: Loreal | O100: 5 | P100: 5246 | Q100: 7518.73 | R100: 10 | S100: 33834.28 | T100: 11363.65 | U100: Debit Card | V100: In Transit | W100: 3 | X100: Chennai Hub | Y100: Kylie May
A101: ORD100099 | B101: CUST10099 | C101: Katie Wood | D101: Male | E101: 45 | F101: Flipkart | G101: 45788 | H101: 46068 | I101: Telangana | J101: Hyderabad | K101: Electronics | L101: P7679 | M101: iPhone 15 | N101: Apple | O101: 4 | P101: 28717 | Q101: 39628.91 | R101: 10 | S101: 142664.08 | T101: 43647.64 | U101: UPI | V101: Cancelled | W101: 2 | X101: Hyderabad Hub | Y101: Connie Watson
A102: ORD100100 | B102: CUST10100 | C102: David Green | D102: Male | E102: 23 | F102: Amazon | G102: 45844 | H102: 45812 | I102: Delhi | J102: New Delhi | K102: Electronics | L102: P8090 | M102: Galaxy S24 | N102: Samsung | O102: 5 | P102: 16510 | Q102: 23961.54 | R102: 5 | S102: 113817.32 | T102: 37257.7 | U102: Debit Card | V102: In Transit | W102: 1 | X102: New Delhi Hub | Y102: Mikayla Jimenez
A103: ORD100101 | B103: CUST10101 | C103: Tony Watson | D103: Female | E103: 35 | F103: Amazon | G103: 45767 | H103: 45646 | I103: Karnataka | J103: Bengaluru | K103: Electronics | L103: P9602 | M103: Galaxy S24 | N103: Samsung | O103: 2 | P103: 1296 | Q103: 1819.66 | R103: 0 | S103: 3639.32 | T103: 1047.32 | U103: Debit Card | V103: Returned | W103: 2 | X103: Bengaluru Hub | Y103: Matthew Obrien
A104: ORD100102 | B104: CUST10102 | C104: Jordan Archer | D104: Female | E104: 26 | F104: Amazon | G104: 45964 | H104: 45871 | I104: Tamil Nadu | J104: Chennai | K104: Electronics | L104: P4662 | M104: iPhone 15 | N104: Apple | O104: 1 | P104: 23879 | Q104: 34067.44 | R104: 10 | S104: 30660.7 | T104: 10188.44 | U104: Credit Card | V104: Delivered | W104: 2 | X104: Chennai Hub | Y104: Joseph Chase
... A115: ORD100113 | B115: CUST10113 | C115: Anthony Rich | D115: Female | E115: 20 | F115: Amazon | G115: 46106 | H115: 45527 | I115: Telangana | J115: Hyderabad | K115: Grocery | L115: P7382 | M115: Sunflower Oil | N115: Fortune | O115: 2 | P115: 8191 | Q115: 10201.24 | R115: 20 | S115: 16321.98 | T115: 4020.48 | U115: Debit Card | V115: In Transit | W115: 2 | X115: Hyderabad Hub | Y115: Travis Mack
A116: ORD100114 | B116: CUST10114 | C116: Kyle Hanson | D116: Male | E116: 18 | F116: Flipkart | G116: 45531 | H116: 45844 | I116: Telangana | J116: Hyderabad | K116: Home | L116: P9774 | N116: Prestige | O116: 4 | P116: 13874 | Q116: 15434.55 | R116: 10 | S116: 55564.38 | T116: 6242.2 | U116: Credit Card | V116: In Transit | W116: 3 | X116: Hyderabad Hub | Y116: Monica Frederick MD
A117: ORD100115 | B117: CUST10115 | C117: Mary Allen | D117: Female | E117: 30 | F117: Flipkart | G117: 46103 | H117: 45560 | I117: Karnataka | J117: Bengaluru | K117: Beauty | L117: P3988 | M117: Face Wash | N117: Loreal | O117: 3 | P117: 26179 | Q117: 32962.95 | R117: 10 | S117: 88999.96 | T117: 20351.85 | U117: COD | V117: Delivered | W117: 4 | X117: Bengaluru Hub | Y117: James Williams
A118: ORD100116 | B118: CUST10116 | C118: Cynthia Smith | D118: Male | E118: 52 | F118: Amazon | G118: 45800 | H118: 46167 | I118: Maharashtra | J118: Pune | K118: Electronics | L118: P5845 | M118: Galaxy S24 | N118: Samsung | O118: 5 | P118: 27891 | Q118: 41038.82 | R118: 10 | S118: 184674.69 | T118: 65739.1 | U118: COD | V118: In Transit | W118: 5 | X118: Pune Hub | Y118: Alfred Buchanan
A119: ORD100117 | B119: CUST10117 | C119: Kimberly Gibson | D119: Female | E119: 26 | F119: Flipkart | G119: 45960 | H119: 45990 | I119: Tamil Nadu | J119: Chennai | K119: Fashion | L119: P3569 | M119: Air Max Shoes | N119: Nike | O119: 5 | P119: 12117 | Q119: 15843.51 | R119: 20 | S119: 63374.04 | T119: 18632.55 | U119: Debit Card | V119: In Transit | W119: 5 | X119: Chennai Hub | Y119: Craig Long
A120: ORD100118 | B120: CUST10118 | C120: Peter Summers | D120: Male | E120: 29 | F120: Flipkart | G120: 45513 | H120: 46101 | I120: Delhi | J120: New Delhi | K120: Beauty | L120: P3134 | M120: Face Wash | N120: Loreal | O120: 1 | P120: 23706 | Q120: 29450.29 | R120: 0 | S120: 29450.29 | T120: 5744.29 | U120: Debit Card | V120: Returned | W120: 1 | X120: New Delhi Hub | Y120: Kelly Mosley
A121: ORD100119 | B121: CUST10119 | C121: Kevin Snyder | D121: Male | E121: 48 | F121: Amazon | G121: 46038 | H121: 46077 | I121: Karnataka | J121: Bengaluru | K121: Beauty | L121: P8674 | M121: Face Wash | N121: Loreal | O121: 5 | P121: 28159 | Q121: 41918.15 | R121: 5 | S121: 199111.21 | T121: 68795.75 | U121: UPI | V121: In Transit | W121: 3 | X121: Bengaluru Hub | Y121: Vicki Brown
A122: ORD100120 | B122: CUST10120 | C122: Michael Jensen | D122: Male | E122: 19 | F122: Flipkart | G122: 45722 | H122: 45827 | I122: Delhi | J122: New Delhi | K122: Home | L122: P9806 | M122: Pressure Cooker | N122: Prestige | O122: 2 | P122: 14880 | Q122: 22161.45 | R122: 5 | S122: 42106.75 | T122: 14562.9 | U122: UPI | V122: Returned | W122: 1 | X122: New Delhi Hub | Y122: Nicole Mccann
A123: ORD100121 | B123: CUST10121 | C123: Kathryn Cox | D123: Female | E123: 19 | F123: Flipkart | G123: 45830 | H123: 45520 | I123: Karnataka | J123: Bengaluru | K123: Fashion | L123: P7952 | M123: Air Max Shoes | N123: Nike | O123: 1 | P123: 11729 | Q123: 17452.29 | R123: 10 | S123: 15707.06 | T123: 5723.29 | U123: COD | V123: Delivered | W123: 1 | X123: Bengaluru Hub | Y123: Steven Murray
A124: ORD100122 | B124: CUST10122 | C124: Andrew Holland | D124: Male | E124: 29 | F124: Flipkart | G124: 46069 | H124: 45514 | I124: Tamil Nadu | J124: Chennai | K124: Electronics | L124: P7156 | M124: iPhone 15 | N124: Apple | O124: 3 | P124: 25198 | Q124: 33188.73 | R124: 15 | S124: 84631.26 | T124: 23972.19 | U124: Credit Card | V124: Returned | W124: 4 | X124: Chennai Hub | Y124: Ryan Boyle
A125: ORD100123 | B125: CUST10123 | C125: Emily Pope | D125: Male | E125: 23 | F125: Amazon | G125: 45903 | H125: 46044 | I125: Telangana | J125: Hyderabad | K125: Home | L125: P6362 | M125: Pressure Cooker | N125: Prestige | O125: 2 | P125: 23524 | Q125: 26090.42 | R125: 0 | S125: 52180.84 | T125: 5132.84 | U125: Credit Card | V125: Returned | W125: 3 | X125: Hyderabad Hub | Y125: Richard Castro
A126: ORD100124 | B126: CUST10124 | C126: Tyrone Mckay | D126: Female | E126: 22 | F126: Amazon | G126: 45948 | H126: 45553 | I126: Tamil Nadu | J126: Chennai | K126: Electronics | L126: P6110 | M126: iPhone 15 | N126: Apple | O126: 3 | P126: 19984 | Q126: 24049.15 | R126: 5 | S126: 68540.08 | T126: 12195.45 | U126: COD | V126: Cancelled | W126: 5 | X126: Chennai Hub | Y126: Roy Brown
A127: ORD100125 | B127: CUST10125 | C127: Brandon Cooley | D127: Male | E127: 51 | F127: Flipkart | G127: 45559 | H127: 45884 | I127: Telangana | J127: Hyderabad | K127: Fashion | L127: P8028 | M127: Air Max Shoes | N127: Nike | O127: 3 | P127: 26019 | Q127: 37572.64 | R127: 20 | S127: 90174.34 | T127: 34660.92 | U127: COD | V127: Delivered | W127: 3 | X127: Hyderabad Hub | Y127: John Scott
A128: ORD100126 | B128: CUST10126 | C128: James Kidd | D128: Female | E128: 55 | F128: Flipkart | G128: 45510 | H128: 45668 | I128: Maharashtra | J128: Mumbai | K128: Home | L128: P8736 | M128: Pressure Cooker | N128: Prestige | O128: 3 | P128: 29219 | Q128: 32815.98 | R128: 5 | S128: 93525.54 | T128: 10790.94 | U128: Debit Card | V128: Cancelled | W128: 5 | X128: Mumbai Hub | Y128: Kelsey Richardson
... A130: ORD100128 | B130: CUST10128 | C130: Chelsea Jones | D130: Female | E130: 25 | F130: Flipkart | G130: 45511 | H130: 45864 | I130: Maharashtra | J130: Mumbai | K130: Grocery | L130: P1082 | M130: Sunflower Oil | N130: Fortune | O130: 2 | P130: 10878 | Q130: 13744.18 | R130: 0 | S130: 27488.36 | T130: 5732.36 | U130: Credit Card | V130: Cancelled | W130: 4 | X130: Mumbai Hub | Y130: John Jones
A131: ORD100129 | B131: CUST10129 | C131: Mary Nelson | D131: Male | E131: 32 | F131: Amazon | G131: 45668 | H131: 46011 | I131: Delhi | J131: New Delhi | K131: Electronics | L131: P4486 | N131: Samsung | O131: 1 | P131: 5877 | Q131: 7439 | R131: 5 | S131: 7067.05 | T131: 1562 | U131: COD | V131: In Transit | W131: 2 | X131: New Delhi Hub | Y131: Jeffrey Hodges
A132: ORD100130 | B132: CUST10130 | C132: Cole Rodriguez | D132: Female | E132: 30 | F132: Amazon | G132: 46014 | H132: 45966 | I132: Tamil Nadu | J132: Chennai | K132: Grocery | L132: P7375 | M132: Sunflower Oil | N132: Fortune | O132: 5 | P132: 17429 | Q132: 21115.22 | R132: 20 | S132: 84460.88 | T132: 18431.1 | U132: Debit Card | V132: Cancelled | W132: 4 | X132: Chennai Hub | Y132: Richard Mason
A133: ORD100131 | B133: CUST10131 | C133: Christopher May | D133: Male | E133: 42 | F133: Amazon | G133: 45876 | H133: 45568 | I133: Delhi | J133: New Delhi | K133: Electronics | L133: P6513 | M133: iPhone 15 | N133: Apple | O133: 5 | P133: 12576 | Q133: 13959.98 | R133: 15 | S133: 59329.91 | T133: 6919.9 | U133: COD | V133: Delivered | W133: 3 | X133: New Delhi Hub | Y133: Jennifer Hansen
A134: ORD100132 | B134: CUST10132 | C134: Melissa Juarez | D134: Male | E134: 49 | F134: Flipkart | G134: 46026 | H134: 45559 | I134: Maharashtra | J134: Pune | K134: Home | L134: P8884 | M134: Pressure Cooker | N134: Prestige | O134: 1 | P134: 6157 | Q134: 8892.67 | R134: 20 | S134: 7114.14 | T134: 2735.67 | U134: COD | V134: Cancelled | W134: 2 | X134: Pune Hub | Y134: Robert Castillo
A135: ORD100133 | B135: CUST10133 | C135: Tina Mueller | D135: Male | E135: 50 | F135: Flipkart | G135: 45556 | H135: 45837 | I135: Maharashtra | J135: Mumbai | K135: Fashion | L135: P7369 | M135: Air Max Shoes | N135: Nike | O135: 1 | P135: 25544 | Q135: 36467.4 | R135: 0 | S135: 36467.4 | T135: 10923.4 | U135: Credit Card | V135: In Transit | W135: 4 | X135: Mumbai Hub | Y135: Cynthia Dawson
A136: ORD100134 | B136: CUST10134 | C136: Douglas Caldwell | D136: Female | E136: 39 | F136: Flipkart | G136: 46096 | H136: 46112 | I136: Tamil Nadu | J136: Chennai | K136: Home | L136: P2656 | M136: Pressure Cooker | N136: Prestige | O136: 1 | P136: 22035 | Q136: 28460.75 | R136: 20 | S136: 22768.6 | T136: 6425.75 | U136: COD | V136: In Transit | W136: 3 | X136: Chennai Hub | Y136: Lisa Cox
A137: ORD100135 | B137: CUST10135 | C137: Corey Gomez | D137: Female | E137: 22 | F137: Flipkart | G137: 45742 | H137: 45670 | I137: Maharashtra | J137: Mumbai | K137: Beauty | L137: P9479 | M137: Face Wash | N137: Loreal | O137: 3 | P137: 14869 | Q137: 19124.89 | R137: 0 | S137: 57374.67 | T137: 12767.67 | U137: Credit Card | V137: Delivered | W137: 3 | X137: Mumbai Hub | Y137: Jeffrey Long
A138: ORD100136 | B138: CUST10136 | C138: Calvin Holt | D138: Female | E138: 60 | F138: Amazon | G138: 45723 | H138: 45658 | I138: Delhi | J138: New Delhi | K138: Beauty | L138: P1722 | M138: Face Wash | N138: Loreal | O138: 3 | P138: 6839 | Q138: 9169.26 | R138: 20 | S138: 22006.22 | T138: 6990.78 | U138: Debit Card | V138: Cancelled | W138: 2 | X138: New Delhi Hub | Y138: Catherine Sparks
A139: ORD100137 | B139: CUST10137 | C139: Linda Adkins | D139: Male | E139: 33 | F139: Amazon | G139: 46155 | H139: 45576 | I139: Tamil Nadu | J139: Chennai | K139: Beauty | L139: P4859 | M139: Face Wash | N139: Loreal | O139: 4 | P139: 15832 | Q139: 19711.64 | R139: 20 | S139: 63077.25 | T139: 15518.56 | U139: UPI | V139: Returned | W139: 1 | X139: Chennai Hub | Y139: George Morales
A140: ORD100138 | B140: CUST10138 | C140: Jose Brown | D140: Female | E140: 53 | F140: Amazon | G140: 45494 | H140: 45573 | I140: Delhi | J140: New Delhi | K140: Beauty | L140: P4983 | M140: Face Wash | N140: Loreal | O140: 4 | P140: 27508 | Q140: 40398.1 | R140: 10 | S140: 145433.16 | T140: 51560.4 | U140: COD | V140: Returned | W140: 2 | X140: New Delhi Hub | Y140: Michael Harvey
A141: ORD100139 | B141: CUST10139 | C141: Robert Velasquez DDS | D141: Female | E141: 60 | F141: Flipkart | G141: 45855 | H141: 45699 | I141: Delhi | J141: New Delhi | K141: Electronics | L141: P8232 | M141: iPhone 15 | N141: Apple | O141: 3 | P141: 25438 | Q141: 36129.31 | R141: 0 | S141: 108387.93 | T141: 32073.93 | U141: UPI | V141: Returned | W141: 4 | X141: New Delhi Hub | Y141: Andrea Frazier
A142: ORD100140 | B142: CUST10140 | C142: Tracy Carroll | D142: Female | E142: 43 | F142: Flipkart | G142: 45673 | H142: 46185 | I142: Maharashtra | J142: Mumbai | K142: Home | L142: P5730 | M142: Pressure Cooker | N142: Prestige | O142: 5 | P142: 12769 | Q142: 15971.95 | R142: 5 | S142: 75866.76 | T142: 16014.75 | U142: UPI | V142: Cancelled | W142: 2 | X142: Mumbai Hub | Y142: Erik Smith
A143: ORD100141 | B143: CUST10141 | C143: Karen Nelson | D143: Male | E143: 26 | F143: Flipkart | G143: 45828 | H143: 46135 | I143: Telangana | J143: Hyderabad | K143: Home | L143: P6061 | M143: Pressure Cooker | N143: Prestige | O143: 4 | P143: 13441 | Q143: 16025 | R143: 5 | S143: 60895 | T143: 10336 | U143: Debit Card | V143: In Transit | W143: 3 | X143: Hyderabad Hub | Y143: Mario Tran
... A155: ORD100153 | B155: CUST10153 | C155: Evan Oconnor | D155: Male | E155: 18 | F155: Flipkart | G155: 45746 | H155: 45595 | I155: Tamil Nadu | J155: Chennai | K155: Electronics | L155: P2179 | M155: Galaxy S24 | N155: Samsung | O155: 4 | P155: 21807 | Q155: 27510.05 | R155: 15 | S155: 93534.17 | T155: 22812.2 | U155: Credit Card | V155: Returned | W155: 2 | X155: Chennai Hub | Y155: Alexa Garcia
A156: ORD100154 | B156: CUST10154 | C156: Michael Taylor | D156: Male | E156: 22 | F156: Amazon | G156: 45923 | H156: 46174 | I156: Telangana | J156: Hyderabad | K156: Beauty | L156: P4152 | M156: Face Wash | N156: Loreal | O156: 2 | P156: 12090 | Q156: 16586.75 | R156: 5 | S156: 31514.82 | T156: 8993.5 | U156: Credit Card | V156: Delivered | X156: Hyderabad Hub | Y156: Amy Howard
A157: ORD100155 | B157: CUST10155 | C157: Kurt Obrien | D157: Male | E157: 49 | F157: Amazon | G157: 45567 | H157: 46070 | I157: Tamil Nadu | J157: Chennai | K157: Fashion | L157: P8714 | M157: Air Max Shoes | N157: Nike | O157: 5 | P157: 18135 | Q157: 24057.99 | R157: 10 | S157: 108260.96 | T157: 29614.95 | U157: Debit Card | V157: In Transit | W157: 5 | X157: Chennai Hub | Y157: Chad Hardin
A158: ORD100156 | B158: CUST10156 | C158: Nicole Bennett | D158: Male | E158: 39 | F158: Amazon | G158: 45935 | H158: 45844 | I158: Karnataka | J158: Bengaluru | K158: Grocery | L158: P4440 | M158: Sunflower Oil | N158: Fortune | O158: 3 | P158: 25779 | Q158: 35635.11 | R158: 5 | S158: 101560.06 | T158: 29568.33 | U158: Debit Card | V158: Cancelled | W158: 2 | X158: Bengaluru Hub | Y158: Diane Valencia
A159: ORD100157 | B159: CUST10157 | C159: Michael Webb | D159: Female | E159: 51 | F159: Flipkart | G159: 46159 | H159: 46194 | I159: Maharashtra | J159: Mumbai | K159: Electronics | L159: P1569 | M159: iPhone 15 | N159: Apple | O159: 1 | P159: 9434 | Q159: 13676.34 | R159: 10 | S159: 12308.71 | T159: 4242.34 | U159: COD | V159: Cancelled | W159: 5 | X159: Mumbai Hub | Y159: Sara Bond
...

Sheet Raw_Data

Sheet Cleaned_Data
A1: Order_ID | B1: Customer_ID | C1: Customer_Name | D1: Gender | E1: Age | F1: Platform | G1: Order_Date | H1: Delivery_Date | I1: State | J1: City | K1: Category | L1: Product_ID | M1: Product_Name | N1: Brand | O1: Quantity | P1: Cost_Price | Q1: Selling_Price | R1: Discount_% | S1: Sales | T1: Profit | U1: Payment_Method | V1: Delivery_Status | W1: Customer_Rating | X1: Warehouse | Y1: Salesperson | Z1: Customer_Name2 | AA1: State3 | AB1: City4 | AC1: Category5 | AD1: Product_Name6 | AE1: Brand7 | AF1: Warehouse8 | AG1: Salesperson9
A2: ORD100000 | B2: CUST10000 | C2: Ashley Cox | D2: Female | E2: 35 | F2: Flipkart | G2: 45988 | H2: 46078 | I2: Maharashtra | J2: Mumbai | K2: Home | L2: P4053 | M2: Pressure Cooker | N2: Prestige | O2: 1 | P2: 17415 | Q2: 19836.65 | R2: 20 | S2: 15869.32 | T2: 2421.65 | U2: Debit Card | V2: Cancelled | W2: 1 | X2: Mumbai Hub | Y2: Robin Hodges | Z2: =TRIM(C2) -> Ashley Cox | AA2: =TRIM(I2) -> Maharashtra | AB2: =TRIM(J2) -> Mumbai | AC2: =TRIM(K2) -> Home | AD2: =TRIM(M2) -> Pressure Cooker | AE2: =TRIM(N2) -> Prestige | AF2: =TRIM(X2) -> Mumbai Hub | AG2: =TRIM(Y2) -> Robin Hodges
A3: ORD100001 | B3: CUST10001 | C3: Rebecca Everett | D3: Female | E3: 41 | F3: Flipkart | G3: 45843 | H3: 45577 | I3: Maharashtra | J3: Pune | K3: Grocery | L3: P3274 | M3: Sunflower Oil | N3: Fortune | O3: 4 | P3: 13107 | Q3: 17607.4 | R3: 10 | S3: 63386.64 | T3: 18001.6 | U3: UPI | V3: Cancelled | W3: 2 | X3: Pune Hub | Y3: Austin Mann | Z3: =TRIM(C3) -> Rebecca Everett | AA3: =TRIM(I3) -> Maharashtra | AB3: =TRIM(J3) -> Pune | AC3: =TRIM(K3) -> Grocery | AD3: =TRIM(M3) -> Sunflower Oil | AE3: =TRIM(N3) -> Fortune | AF3: =TRIM(X3) -> Pune Hub | AG3: =TRIM(Y3) -> Austin Mann
A4: ORD100002 | B4: CUST10002 | C4: Jacob Dalton | D4: Male | E4: 22 | F4: Flipkart | G4: 45879 | H4: 45906 | I4: Delhi | J4: New Delhi | K4: Grocery | L4: P1312 | M4: Sunflower Oil | N4: Fortune | O4: 1 | P4: 1905 | Q4: 2290.68 | R4: 15 | S4: 1947.08 | T4: 385.68 | U4: Debit Card | V4: Cancelled | W4: 4 | X4: New Delhi Hub | Y4: Andres Wright | Z4: =TRIM(C4) -> Jacob Dalton | AA4: =TRIM(I4) -> Delhi | AB4: =TRIM(J4) -> New Delhi | AC4: =TRIM(K4) -> Grocery | AD4: =TRIM(M4) -> Sunflower Oil | AE4: =TRIM(N4) -> Fortune | AF4: =TRIM(X4) -> New Delhi Hub | AG4: =TRIM(Y4) -> Andres Wright
A5: ORD100003 | B5: CUST10003 | C5: Diana Murphy DDS | D5: Male | E5: 59 | F5: Flipkart | G5: 45608 | H5: 45927 | I5: Telangana | J5: Hyderabad | K5: Beauty | L5: P3240 | M5: Face Wash | N5: Loreal | O5: 3 | P5: 10574 | Q5: 11718.4 | R5: 20 | S5: 28124.16 | T5: 3433.2 | U5: Debit Card | V5: Delivered | W5: 2 | X5: Hyderabad Hub | Y5: Eugene Martin | Z5: =TRIM(C5) -> Diana Murphy DDS | AA5: =TRIM(I5) -> Telangana | AB5: =TRIM(J5) -> Hyderabad | AC5: =TRIM(K5) -> Beauty | AD5: =TRIM(M5) -> Face Wash | AE5: =TRIM(N5) -> Loreal | AF5: =TRIM(X5) -> Hyderabad Hub | AG5: =TRIM(Y5) -> Eugene Martin
A6: ORD100004 | B6: CUST10004 | C6: Henry Rojas | D6: Female | E6: 55 | F6: Flipkart | G6: 45558 | H6: 45575 | I6: Karnataka | J6: Bengaluru | K6: Beauty | L6: P5574 | M6: Face Wash | N6: Loreal | O6: 5 | P6: 19031 | Q6: 27531.63 | R6: 15 | S6: 117009.43 | T6: 42503.15 | U6: Credit Card | V6: Delivered | W6: 4 | X6: Bengaluru Hub | Y6: Amy Contreras | Z6: =TRIM(C6) -> Henry Rojas | AA6: =TRIM(I6) -> Karnataka | AB6: =TRIM(J6) -> Bengaluru | AC6: =TRIM(K6) -> Beauty | AD6: =TRIM(M6) -> Face Wash | AE6: =TRIM(N6) -> Loreal | AF6: =TRIM(X6) -> Bengaluru Hub | AG6: =TRIM(Y6) -> Amy Contreras
A7: ORD100005 | B7: CUST10005 | C7: Morgan Robinson | D7: Male | E7: 48 | F7: Flipkart | G7: 46027 | H7: 45728 | I7: Tamil Nadu | J7: Chennai | K7: Grocery | L7: P3562 | M7: Sunflower Oil | N7: Fortune | O7: 4 | P7: 7382 | Q7: 9091.91 | R7: 5 | S7: 34549.26 | T7: 6839.64 | U7: UPI | V7: Delivered | W7: 1 | X7: Chennai Hub | Y7: Mckenzie Brady | Z7: =TRIM(C7) -> Morgan Robinson | AA7: =TRIM(I7) -> Tamil Nadu | AB7: =TRIM(J7) -> Chennai | AC7: =TRIM(K7) -> Grocery | AD7: =TRIM(M7) -> Sunflower Oil | AE7: =TRIM(N7) -> Fortune | AF7: =TRIM(X7) -> Chennai Hub | AG7: =TRIM(Y7) -> Mckenzie Brady
A8: ORD100006 | B8: CUST10006 | C8: Robert Peterson | D8: Female | E8: 32 | F8: Amazon | G8: 45610 | H8: 46130 | I8: Telangana | J8: Hyderabad | K8: Electronics | L8: P2671 | M8: Galaxy S24 | N8: Samsung | O8: 2 | P8: 26006 | Q8: 29271.93 | R8: 0 | S8: 58543.86 | T8: 6531.86 | U8: Debit Card | V8: Cancelled | W8: 5 | X8: Hyderabad Hub | Y8: Michele Taylor | Z8: =TRIM(C8) -> Robert Peterson | AA8: =TRIM(I8) -> Telangana | AB8: =TRIM(J8) -> Hyderabad | AC8: =TRIM(K8) -> Electronics | AD8: =TRIM(M8) -> Galaxy S24 | AE8: =TRIM(N8) -> Samsung | AF8: =TRIM(X8) -> Hyderabad Hub | AG8: =TRIM(Y8) -> Michele Taylor
A9: ORD100007 | B9: CUST10007 | C9: Lindsey Brown | D9: Male | E9: 54 | F9: Flipkart | G9: 45708 | H9: 45634 | I9: Karnataka | J9: Bengaluru | K9: Beauty | L9: P3840 | M9: Face Wash | N9: Loreal | O9: 3 | P9: 9411 | Q9: 12520.75 | R9: 15 | S9: 31927.91 | T9: 9329.25 | U9: Debit Card | V9: Delivered | W9: 2 | X9: Bengaluru Hub | Y9: Christina Stevens | Z9: =TRIM(C9) -> Lindsey Brown | AA9: =TRIM(I9) -> Karnataka | AB9: =TRIM(J9) -> Bengaluru | AC9: =TRIM(K9) -> Beauty | AD9: =TRIM(M9) -> Face Wash | AE9: =TRIM(N9) -> Loreal | AF9: =TRIM(X9) -> Bengaluru Hub | AG9: =TRIM(Y9) -> Christina Stevens
A10: ORD100008 | B10: CUST10008 | C10: Charlotte Gilbert | D10: Female | E10: 46 | F10: Flipkart | G10: 45611 | H10: 45792 | I10: Maharashtra | J10: Mumbai | K10: Grocery | L10: P5256 | M10: Sunflower Oil | N10: Fortune | O10: 3 | P10: 18006 | Q10: 20107.58 | R10: 10 | S10: 54290.47 | T10: 6304.74 | U10: Debit Card | V10: Cancelled | W10: 3 | X10: Mumbai Hub | Y10: Clifford Newton | Z10: =TRIM(C10) -> Charlotte Gilbert | AA10: =TRIM(I10) -> Maharashtra | AB10: =TRIM(J10) -> Mumbai | AC10: =TRIM(K10) -> Grocery | AD10: =TRIM(M10) -> Sunflower Oil | AE10: =TRIM(N10) -> Fortune | AF10: =TRIM(X10) -> Mumbai Hub | AG10: =TRIM(Y10) -> Clifford Newton
A11: ORD100009 | B11: CUST10009 | C11: Rachel Garcia | D11: Male | E11: 32 | F11: Flipkart | G11: 46067 | H11: 45805 | I11: Karnataka | J11: Bengaluru | K11: Beauty | L11: P3816 | M11: Face Wash | N11: Loreal | O11: 2 | P11: 2839 | Q11: 3511.61 | R11: 20 | S11: 5618.58 | T11: 1345.22 | U11: Credit Card | V11: In Transit | W11: 4 | X11: Bengaluru Hub | Y11: Jerome Campbell | Z11: =TRIM(C11) -> Rachel Garcia | AA11: =TRIM(I11) -> Karnataka | AB11: =TRIM(J11) -> Bengaluru | AC11: =TRIM(K11) -> Beauty | AD11: =TRIM(M11) -> Face Wash | AE11: =TRIM(N11) -> Loreal | AF11: =TRIM(X11) -> Bengaluru Hub | AG11: =TRIM(Y11) -> Jerome Campbell
A12: ORD100010 | B12: CUST10010 | C12: Travis Keller | D12: Female | E12: 46 | F12: Amazon | G12: 46069 | H12: 45474 | I12: Delhi | J12: New Delhi | K12: Fashion | L12: P2051 | M12: Air Max Shoes | N12: Nike | O12: 5 | P12: 15167 | Q12: 19780.36 | R12: 5 | S12: 93956.71 | T12: 23066.8 | U12: UPI | V12: Delivered | W12: 1 | X12: New Delhi Hub | Y12: Anthony Day | Z12: =TRIM(C12) -> Travis Keller | AA12: =TRIM(I12) -> Delhi | AB12: =TRIM(J12) -> New Delhi | AC12: =TRIM(K12) -> Fashion | AD12: =TRIM(M12) -> Air Max Shoes | AE12: =TRIM(N12) -> Nike | AF12: =TRIM(X12) -> New Delhi Hub | AG12: =TRIM(Y12) -> Anthony Day
A13: ORD100011 | B13: CUST10011 | C13: Joshua Thompson | D13: Female | E13: 19 | F13: Flipkart | G13: 45854 | H13: 45561 | I13: Telangana | J13: Hyderabad | K13: Fashion | L13: P5949 | M13: Air Max Shoes | N13: Nike | O13: 4 | P13: 12428 | Q13: 15530.69 | R13: 0 | S13: 62122.76 | T13: 12410.76 | U13: COD | V13: Delivered | W13: 3 | X13: Hyderabad Hub | Y13: Devin Johnson | Z13: =TRIM(C13) -> Joshua Thompson | AA13: =TRIM(I13) -> Telangana | AB13: =TRIM(J13) -> Hyderabad | AC13: =TRIM(K13) -> Fashion | AD13: =TRIM(M13) -> Air Max Shoes | AE13: =TRIM(N13) -> Nike | AF13: =TRIM(X13) -> Hyderabad Hub | AG13: =TRIM(Y13) -> Devin Johnson
... A38: ORD100036 | B38: CUST10036 | C38: Sheila Townsend | D38: Female | E38: 49 | F38: Flipkart | G38: 46181 | H38: 45658 | I38: Tamil Nadu | J38: Chennai | K38: Fashion | L38: P1779 | M38: Air Max Shoes | N38: Nike | O38: 1 | P38: 26287 | Q38: 37421.5 | R38: 20 | S38: 29937.2 | T38: 11134.5 | U38: Debit Card | V38: In Transit | W38: 5 | X38: Chennai Hub | Y38: Kenneth Jackson | Z38: =TRIM(C38) -> Sheila Townsend | AA38: =TRIM(I38) -> Tamil Nadu | AB38: =TRIM(J38) -> Chennai | AC38: =TRIM(K38) -> Fashion | AD38: =TRIM(M38) -> Air Max Shoes | AE38: =TRIM(N38) -> Nike | AF38: =TRIM(X38) -> Chennai Hub | AG38: =TRIM(Y38) -> Kenneth Jackson
A39: ORD100037 | B39: CUST10037 | C39: Garrett Arnold | D39: Male | E39: 36 | F39: Amazon | G39: 45787 | H39: 46061 | J39: Mumbai | K39: Grocery | L39: P2750 | M39: Sunflower Oil | N39: Fortune | O39: 1 | P39: 7793 | Q39: 10301.16 | R39: 0 | S39: 10301.16 | T39: 2508.16 | U39: COD | V39: Cancelled | W39: 4 | X39: Mumbai Hub | Y39: Jessica Lewis | Z39: =TRIM(C39) -> Garrett Arnold | AA39: Maharashtra | AB39: =TRIM(J39) -> Mumbai | AC39: =TRIM(K39) -> Grocery | AD39: =TRIM(M39) -> Sunflower Oil | AE39: =TRIM(N39) -> Fortune | AF39: =TRIM(X39) -> Mumbai Hub | AG39: =TRIM(Y39) -> Jessica Lewis
A40: ORD100038 | B40: CUST10038 | C40: Louis Johnston | D40: Female | E40: 27 | F40: Flipkart | G40: 45902 | H40: 45763 | I40: Delhi | J40: New Delhi | K40: Electronics | L40: P5210 | M40: Galaxy S24 | N40: Samsung | O40: 4 | P40: 2289 | Q40: 3275.78 | R40: 5 | S40: 12447.96 | T40: 3947.12 | U40: Debit Card | V40: Delivered | W40: 3 | X40: New Delhi Hub | Y40: James Alexander | Z40: =TRIM(C40) -> Louis Johnston | AA40: =TRIM(I40) -> Delhi | AB40: =TRIM(J40) -> New Delhi | AC40: =TRIM(K40) -> Electronics | AD40: =TRIM(M40) -> Galaxy S24 | AE40: =TRIM(N40) -> Samsung | AF40: =TRIM(X40) -> New Delhi Hub | AG40: =TRIM(Y40) -> James Alexander
A41: ORD100039 | B41: CUST10039 | C41: Nicole Mckenzie | D41: Male | E41: 26 | F41: Flipkart | G41: 46037 | H41: 45476 | I41: Karnataka | J41: Bengaluru | K41: Beauty | L41: P7944 | M41: Face Wash | N41: Loreal | O41: 5 | P41: 7115 | Q41: 7914.96 | R41: 0 | S41: 39574.8 | T41: 3999.8 | U41: UPI | V41: In Transit | W41: 3 | X41: Bengaluru Hub | Y41: Sarah Robinson | Z41: =TRIM(C41) -> Nicole Mckenzie | AA41: =TRIM(I41) -> Karnataka | AB41: =TRIM(J41) -> Bengaluru | AC41: =TRIM(K41) -> Beauty | AD41: =TRIM(M41) -> Face Wash | AE41: =TRIM(N41) -> Loreal | AF41: =TRIM(X41) -> Bengaluru Hub | AG41: =TRIM(Y41) -> Sarah Robinson
A42: ORD100040 | B42: CUST10040 | C42: Alexis Richardson | D42: Female | E42: 58 | F42: Amazon | G42: 45876 | H42: 45975 | I42: Maharashtra | J42: Pune | K42: Electronics | L42: P7018 | M42: iPhone 15 | N42: Apple | O42: 2 | P42: 25274 | Q42: 36619.98 | R42: 15 | S42: 62253.97 | T42: 22691.96 | U42: Credit Card | V42: Returned | W42: 5 | X42: Pune Hub | Y42: Patricia Gardner | Z42: =TRIM(C42) -> Alexis Richardson | AA42: =TRIM(I42) -> Maharashtra | AB42: =TRIM(J42) -> Pune | AC42: =TRIM(K42) -> Electronics | AD42: =TRIM(M42) -> iPhone 15 | AE42: =TRIM(N42) -> Apple | AF42: =TRIM(X42) -> Pune Hub | AG42: =TRIM(Y42) -> Patricia Gardner
A43: ORD100041 | B43: CUST10041 | C43: Jennifer Edwards | D43: Female | E43: 21 | F43: Flipkart | G43: 45859 | H43: 45904 | I43: Telangana | J43: Hyderabad | K43: Fashion | L43: P4859 | M43: Air Max Shoes | N43: Nike | O43: 4 | P43: 18988 | Q43: 21837.44 | R43: 15 | S43: 74247.3 | T43: 11397.76 | U43: COD | V43: Delivered | W43: 5 | X43: Hyderabad Hub | Y43: Alexa Wiley | Z43: =TRIM(C43) -> Jennifer Edwards | AA43: =TRIM(I43) -> Telangana | AB43: =TRIM(J43) -> Hyderabad | AC43: =TRIM(K43) -> Fashion | AD43: =TRIM(M43) -> Air Max Shoes | AE43: =TRIM(N43) -> Nike | AF43: =TRIM(X43) -> Hyderabad Hub | AG43: =TRIM(Y43) -> Alexa Wiley
A44: ORD100042 | B44: CUST10042 | C44: Russell Monroe | D44: Female | E44: 37 | F44: Amazon | G44: 46027 | H44: 45597 | I44: Delhi | J44: New Delhi | K44: Home | L44: P5990 | M44: Pressure Cooker | N44: Prestige | O44: 4 | P44: 20396 | Q44: 26976.2 | R44: 0 | S44: 107904.8 | T44: 26320.8 | U44: Debit Card | V44: In Transit | W44: 4 | X44: New Delhi Hub | Y44: Dr. Brian Miller | Z44: =TRIM(C44) -> Russell Monroe | AA44: =TRIM(I44) -> Delhi | AB44: =TRIM(J44) -> New Delhi | AC44: =TRIM(K44) -> Home | AD44: =TRIM(M44) -> Pressure Cooker | AE44: =TRIM(N44) -> Prestige | AF44: =TRIM(X44) -> New Delhi Hub | AG44: =TRIM(Y44) -> Dr. Brian Miller
A45: ORD100043 | B45: CUST10043 | C45: Sara Weaver | D45: Male | E45: 57 | F45: Flipkart | G45: 46129 | H45: 45929 | I45: Maharashtra | J45: Pune | K45: Electronics | L45: P5182 | M45: Galaxy S24 | N45: Samsung | O45: 3 | P45: 2760 | Q45: 3800.52 | R45: 0 | S45: 11401.56 | T45: 3121.56 | U45: COD | V45: Returned | W45: 3 | X45: Pune Hub | Y45: Charles Fitzgerald | Z45: =TRIM(C45) -> Sara Weaver | AA45: =TRIM(I45) -> Maharashtra | AB45: =TRIM(J45) -> Pune | AC45: =TRIM(K45) -> Electronics | AD45: =TRIM(M45) -> Galaxy S24 | AE45: =TRIM(N45) -> Samsung | AF45: =TRIM(X45) -> Pune Hub | AG45: =TRIM(Y45) -> Charles Fitzgerald
A46: ORD100044 | B46: CUST10044 | C46: Eric Harris | D46: Male | E46: 55 | F46: Amazon | G46: 45924 | H46: 45940 | I46: Delhi | J46: New Delhi | K46: Electronics | L46: P6167 | M46: Galaxy S24 | N46: Samsung | O46: 4 | P46: 16611 | Q46: 18707.32 | R46: 5 | S46: 71087.82 | T46: 8385.28 | U46: UPI | V46: Cancelled | W46: 1 | X46: New Delhi Hub | Y46: Richard Schaefer | Z46: =TRIM(C46) -> Eric Harris | AA46: =TRIM(I46) -> Delhi | AB46: =TRIM(J46) -> New Delhi | AC46: =TRIM(K46) -> Electronics | AD46: =TRIM(M46) -> Galaxy S24 | AE46: =TRIM(N46) -> Samsung | AF46: =TRIM(X46) -> New Delhi Hub | AG46: =TRIM(Y46) -> Richard Schaefer
A47: ORD100045 | B47: CUST10045 | C47: Amanda Elliott | D47: Female | E47: 54 | F47: Flipkart | G47: 46093 | H47: 45902 | I47: Delhi | J47: New Delhi | K47: Electronics | L47: P7269 | M47: Galaxy S24 | N47: Samsung | O47: 3 | P47: 29223 | Q47: 38901.68 | R47: 5 | S47: 110869.79 | T47: 29036.04 | U47: COD | V47: Delivered | W47: 1 | X47: New Delhi Hub | Y47: Benjamin Mora | Z47: =TRIM(C47) -> Amanda Elliott | AA47: =TRIM(I47) -> Delhi | AB47: =TRIM(J47) -> New Delhi | AC47: =TRIM(K47) -> Electronics | AD47: =TRIM(M47) -> Galaxy S24 | AE47: =TRIM(N47) -> Samsung | AF47: =TRIM(X47) -> New Delhi Hub | AG47: =TRIM(Y47) -> Benjamin Mora
A48: ORD100046 | B48: CUST10046 | C48: Annette Payne | D48: Male | E48: 42 | F48: Flipkart | G48: 46144 | H48: 45907 | I48: Maharashtra | J48: Chennai | K48: Electronics | L48: P5807 | N48: Prestige | O48: 5 | P48: 20367 | Q48: 25753.96 | R48: 15 | S48: 109454.33 | T48: 26934.8 | U48: UPI | V48: Delivered | W48: 5 | X48: Chennai Hub | Y48: Nicole Torres | Z48: =TRIM(C48) -> Annette Payne | AA48: =TRIM(I48) -> Maharashtra | AB48: =TRIM(J48) -> Chennai | AC48: =TRIM(K48) -> Electronics | AD48: Pressure Cooker | AE48: =TRIM(N48) -> Prestige | AF48: =TRIM(X48) -> Chennai Hub | AG48: =TRIM(Y48) -> Nicole Torres
A49: ORD100047 | B49: CUST10047 | C49: Aaron Clark MD | D49: Female | E49: 57 | F49: Flipkart | G49: 45707 | H49: 46002 | I49: Delhi | J49: New Delhi | K49: Electronics | L49: P5991 | M49: Face Wash | N49: Loreal | O49: 2 | P49: 5958 | Q49: 6718.88 | R49: 20 | S49: 10750.21 | T49: 1521.76 | U49: Debit Card | V49: Cancelled | W49: 3 | X49: New Delhi Hub | Y49: Marvin Floyd | Z49: =TRIM(C49) -> Aaron Clark MD | AA49: =TRIM(I49) -> Delhi | AB49: =TRIM(J49) -> New Delhi | AC49: =TRIM(K49) -> Electronics | AD49: =TRIM(M49) -> Face Wash | AE49: =TRIM(N49) -> Loreal | AF49: =TRIM(X49) -> New Delhi Hub | AG49: =TRIM(Y49) -> Marvin Floyd
A50: ORD100048 | B50: CUST10048 | C50: Daniel Nichols | D50: Male | E50: 18 | F50: Flipkart | G50: 45683 | H50: 46170 | I50: Maharashtra | J50: Pune | K50: Beauty | L50: P5731 | M50: Face Wash | N50: Loreal | O50: 5 | P50: 29365 | Q50: 38587.11 | R50: 10 | S50: 173641.99 | T50: 46110.55 | U50: Credit Card | V50: Delivered | W50: 2 | X50: Pune Hub | Y50: Andrea Wolfe | Z50: =TRIM(C50) -> Daniel Nichols | AA50: =TRIM(I50) -> Maharashtra | AB50: =TRIM(J50) -> Pune | AC50: =TRIM(K50) -> Beauty | AD50: =TRIM(M50) -> Face Wash | AE50: =TRIM(N50) -> Loreal | AF50: =TRIM(X50) -> Pune Hub | AG50: =TRIM(Y50) -> Andrea Wolfe
A51: ORD100049 | B51: CUST10049 | C51: Cody Singh | D51: Male | E51: 60 | F51: Amazon | G51: 45772 | H51: 45532 | I51: Telangana | J51: Hyderabad | K51: Electronics | L51: P2525 | M51: Galaxy S24 | N51: Samsung | O51: 1 | P51: 21589 | Q51: 26488.47 | R51: 10 | S51: 23839.62 | T51: 4899.47 | U51: Debit Card | V51: Cancelled | W51: 3 | X51: Hyderabad Hub | Y51: Vickie Turner | Z51: =TRIM(C51) -> Cody Singh | AA51: =TRIM(I51) -> Telangana | AB51: =TRIM(J51) -> Hyderabad | AC51: =TRIM(K51) -> Electronics | AD51: =TRIM(M51) -> Galaxy S24 | AE51: =TRIM(N51) -> Samsung | AF51: =TRIM(X51) -> Hyderabad Hub | AG51: =TRIM(Y51) -> Vickie Turner
A52: ORD100050 | B52: CUST10050 | C52: Jennifer Welch | D52: Male | E52: 24 | F52: Amazon | G52: 45811 | H52: 45533 | J52: Chennai | K52: Electronics | L52: P2909 | N52: Apple | O52: 2 | P52: 20982 | Q52: 27502.55 | R52: 10 | S52: 49504.59 | T52: 13041.1 | U52: COD | V52: Delivered | W52: 2 | X52: Chennai Hub | Y52: Elizabeth Moore | Z52: =TRIM(C52) -> Jennifer Welch | AA52: Tamil Nadu | AB52: =TRIM(J52) -> Chennai | AC52: =TRIM(K52) -> Electronics | AD52: iPhone 15 | AE52: =TRIM(N52) -> Apple | AF52: =TRIM(X52) -> Chennai Hub | AG52: =TRIM(Y52) -> Elizabeth Moore
A53: ORD100051 | B53: CUST10051 | C53: Dan Lewis | D53: Female | E53: 36 | F53: Flipkart | G53: 45997 | H53: 45503 | I53: Telangana | J53: Hyderabad | K53: Home | L53: P1231 | M53: Pressure Cooker | N53: Prestige | O53: 5 | P53: 15977 | Q53: 21699.83 | R53: 15 | S53: 92224.28 | T53: 28614.15 | U53: Credit Card | V53: In Transit | W53: 3 | X53: Hyderabad Hub | Y53: Veronica Mays | Z53: =TRIM(C53) -> Dan Lewis | AA53: =TRIM(I53) -> Telangana | AB53: =TRIM(J53) -> Hyderabad | AC53: =TRIM(K53) -> Home | AD53: =TRIM(M53) -> Pressure Cooker | AE53: =TRIM(N53) -> Prestige | AF53: =TRIM(X53) -> Hyderabad Hub | AG53: =TRIM(Y53) -> Veronica Mays
A54: ORD100052 | B54: CUST10052 | C54: Rachel Weber | D54: Male | E54: 57 | F54: Amazon | G54: 46139 | H54: 45760 | I54: Maharashtra | J54: Pune | K54: Fashion | L54: P4664 | M54: Air Max Shoes | N54: Nike | O54: 1 | P54: 28567 | Q54: 38920.04 | R54: 15 | S54: 33082.03 | T54: 10353.04 | U54: UPI | V54: Delivered | W54: 2 | X54: Pune Hub | Y54: Cynthia Schwartz | Z54: =TRIM(C54) -> Rachel Weber | AA54: =TRIM(I54) -> Maharashtra | AB54: =TRIM(J54) -> Pune | AC54: =TRIM(K54) -> Fashion | AD54: =TRIM(M54) -> Air Max Shoes | AE54: =TRIM(N54) -> Nike | AF54: =TRIM(X54) -> Pune Hub | AG54: =TRIM(Y54) -> Cynthia Schwartz
A55: ORD100053 | B55: CUST10053 | C55: Henry Graves | D55: Male | E55: 43 | F55: Amazon | G55: 46026 | H55: 45490 | I55: Tamil Nadu | J55: Chennai | K55: Grocery | L55: P3946 | M55: Sunflower Oil | N55: Fortune | O55: 5 | P55: 4075 | Q55: 5183.29 | R55: 0 | S55: 25916.45 | T55: 5541.45 | U55: Credit Card | V55: Returned | W55: 3 | X55: Chennai Hub | Y55: Pamela White MD | Z55: =TRIM(C55) -> Henry Graves | AA55: =TRIM(I55) -> Tamil Nadu | AB55: =TRIM(J55) -> Chennai | AC55: =TRIM(K55) -> Grocery | AD55: =TRIM(M55) -> Sunflower Oil | AE55: =TRIM(N55) -> Fortune | AF55: =TRIM(X55) -> Chennai Hub | AG55: =TRIM(Y55) -> Pamela White MD
A56: ORD100054 | B56: CUST10054 | C56: Angela Owen | D56: Male | E56: 56 | F56: Amazon | G56: 45917 | H56: 45866 | I56: Maharashtra | J56: Pune | K56: Fashion | L56: P4171 | M56: Air Max Shoes | N56: Nike | O56: 3 | P56: 10999 | Q56: 13707.58 | R56: 10 | S56: 37010.47 | T56: 8125.74 | U56: UPI | V56: Returned | W56: 3 | X56: Pune Hub | Y56: Nancy Martinez | Z56: =TRIM(C56) -> Angela Owen | AA56: =TRIM(I56) -> Maharashtra | AB56: =TRIM(J56) -> Pune | AC56: =TRIM(K56) -> Fashion | AD56: =TRIM(M56) -> Air Max Shoes | AE56: =TRIM(N56) -> Nike | AF56: =TRIM(X56) -> Pune Hub | AG56: =TRIM(Y56) -> Nancy Martinez
A57: ORD100055 | B57: CUST10055 | C57: Garrett Garcia | D57: Male | E57: 41 | F57: Flipkart | G57: 45795 | H57: 45638 | I57: Telangana | J57: Hyderabad | K57: Electronics | L57: P9891 | M57: iPhone 15 | N57: Apple | O57: 4 | P57: 29239 | Q57: 37702.11 | R57: 20 | S57: 120646.75 | T57: 33852.44 | U57: COD | V57: In Transit | W57: 3 | X57: Hyderabad Hub | Y57: Julie Brown | Z57: =TRIM(C57) -> Garrett Garcia | AA57: =TRIM(I57) -> Telangana | AB57: =TRIM(J57) -> Hyderabad | AC57: =TRIM(K57) -> Electronics | AD57: =TRIM(M57) -> iPhone 15 | AE57: =TRIM(N57) -> Apple | AF57: =TRIM(X57) -> Hyderabad Hub | AG57: =TRIM(Y57) -> Julie Brown
A58: ORD100056 | B58: CUST10056 | C58: Danielle Smith | D58: Female | E58: 30 | F58: Amazon | G58: 46039 | H58: 45587 | I58: Delhi | J58: New Delhi | K58: Grocery | L58: P7484 | M58: Sunflower Oil | N58: Fortune | O58: 4 | P58: 22526 | Q58: 25803.23 | R58: 0 | S58: 103212.92 | T58: 13108.92 | U58: Credit Card | V58: Delivered | W58: 5 | X58: New Delhi Hub | Y58: James Lynch | Z58: =TRIM(C58) -> Danielle Smith | AA58: =TRIM(I58) -> Delhi | AB58: =TRIM(J58) -> New Delhi | AC58: =TRIM(K58) -> Grocery | AD58: =TRIM(M58) -> Sunflower Oil | AE58: =TRIM(N58) -> Fortune | AF58: =TRIM(X58) -> New Delhi Hub | AG58: =TRIM(Y58) -> James Lynch
A59: ORD100057 | B59: CUST10057 | C59: Ana Willis | D59: Male | E59: 32 | F59: Amazon | G59: 45923 | H59: 46053 | I59: Delhi | J59: New Delhi | K59: Electronics | L59: P1584 | M59: Galaxy S24 | N59: Samsung | O59: 3 | P59: 20408 | Q59: 25911.99 | R59: 20 | S59: 62188.78 | T59: 16511.97 | U59: UPI | V59: Delivered | W59: 4 | X59: New Delhi Hub | Y59: Paul Sanchez | Z59: =TRIM(C59) -> Ana Willis | AA59: =TRIM(I59) -> Delhi | AB59: =TRIM(J59) -> New Delhi | AC59: =TRIM(K59) -> Electronics | AD59: =TRIM(M59) -> Galaxy S24 | AE59: =TRIM(N59) -> Samsung | AF59: =TRIM(X59) -> New Delhi Hub | AG59: =TRIM(Y59) -> Paul Sanchez
A60: ORD100058 | B60: CUST10058 | C60: Briana Nguyen | D60: Female | E60: 35 | F60: Flipkart | G60: 45925 | H60: 45601 | I60: Tamil Nadu | J60: Chennai | K60: Grocery | L60: P1067 | M60: Sunflower Oil | N60: Fortune | O60: 3 | P60: 15427 | Q60: 22409.45 | R60: 20 | S60: 53782.68 | T60: 20947.35 | U60: Credit Card | V60: Delivered | W60: 3 | X60: Chennai Hub | Y60: Michaela Huffman | Z60: =TRIM(C60) -> Briana Nguyen | AA60: =TRIM(I60) -> Tamil Nadu | AB60: =TRIM(J60) -> Chennai | AC60: =TRIM(K60) -> Grocery | AD60: =TRIM(M60) -> Sunflower Oil | AE60: =TRIM(N60) -> Fortune | AF60: =TRIM(X60) -> Chennai Hub | AG60: =TRIM(Y60) -> Michaela Huffman
A61: ORD100059 | B61: CUST10059 | C61: Theresa Spence | D61: Female | E61: 39 | F61: Amazon | G61: 46017 | H61: 46156 | I61: Tamil Nadu | J61: Chennai | K61: Fashion | L61: P1165 | M61: Air Max Shoes | N61: Nike | O61: 4 | P61: 7700 | Q61: 10108.3 | R61: 5 | S61: 38411.54 | T61: 9633.2 | U61: Credit Card | V61: Cancelled | W61: 3 | X61: Chennai Hub | Y61: Jonathan Vasquez MD | Z61: =TRIM(C61) -> Theresa Spence | AA61: =TRIM(I61) -> Tamil Nadu | AB61: =TRIM(J61) -> Chennai | AC61: =TRIM(K61) -> Fashion | AD61: =TRIM(M61) -> Air Max Shoes | AE61: =TRIM(N61) -> Nike | AF61: =TRIM(X61) -> Chennai Hub | AG61: =TRIM(Y61) -> Jonathan Vasquez MD
A62: ORD100060 | B62: CUST10060 | C62: Ashley Mann | D62: Female | E62: 41 | F62: Flipkart | G62: 46158 | H62: 45785 | I62: Karnataka | J62: Bengaluru | K62: Electronics | L62: P3831 | M62: Galaxy S24 | N62: Samsung | O62: 2 | P62: 21776 | Q62: 32410.34 | R62: 0 | S62: 64820.68 | T62: 21268.68 | U62: COD | V62: Cancelled | W62: 1 | X62: Bengaluru Hub | Y62: James Wells | Z62: =TRIM(C62) -> Ashley Mann | AA62: =TRIM(I62) -> Karnataka | AB62: =TRIM(J62) -> Bengaluru | AC62: =TRIM(K62) -> Electronics | AD62: =TRIM(M62) -> Galaxy S24 | AE62: =TRIM(N62) -> Samsung | AF62: =TRIM(X62) -> Bengaluru Hub | AG62: =TRIM(Y62) -> James Wells
A63: ORD100061 | B63: CUST10061 | C63: Vincent Anderson | D63: Female | E63: 31 | F63: Amazon | G63: 46026 | H63: 45677 | I63: Telangana | J63: Hyderabad | K63: Electronics | L63: P3580 | M63: iPhone 15 | N63: Apple | O63: 1 | P63: 8685 | Q63: 9884.19 | R63: 0 | S63: 9884.19 | T63: 1199.19 | U63: Debit Card | V63: Cancelled | W63: 2 | X63: Hyderabad Hub | Y63: Mary Nichols | Z63: =TRIM(C63) -> Vincent Anderson | AA63: =TRIM(I63) -> Telangana | AB63: =TRIM(J63) -> Hyderabad | AC63: =TRIM(K63) -> Electronics | AD63: =TRIM(M63) -> iPhone 15 | AE63: =TRIM(N63) -> Apple | AF63: =TRIM(X63) -> Hyderabad Hub | AG63: =TRIM(Y63) -> Mary Nichols
A64: ORD100062 | B64: CUST10062 | C64: Jennifer Simpson | D64: Female | E64: 36 | F64: Flipkart | G64: 45492 | H64: 45496 | I64: Karnataka | J64: Bengaluru | K64: Fashion | L64: P1951 | M64: Air Max Shoes | N64: Nike | O64: 2 | P64: 19331 | Q64: 25103.5 | R64: 10 | S64: 45186.3 | T64: 11545 | U64: UPI | V64: Cancelled | W64: 5 | X64: Bengaluru Hub | Y64: Melanie Garrett | Z64: =TRIM(C64) -> Jennifer Simpson | AA64: =TRIM(I64) -> Karnataka | AB64: =TRIM(J64) -> Bengaluru | AC64: =TRIM(K64) -> Fashion | AD64: =TRIM(M64) -> Air Max Shoes | AE64: =TRIM(N64) -> Nike | AF64: =TRIM(X64) -> Bengaluru Hub | AG64: =TRIM(Y64) -> Melanie Garrett
... A86: ORD100084 | B86: CUST10084 | C86: David Price | D86: Male | E86: 28 | F86: Flipkart | G86: 45476 | H86: 45524 | I86: Telangana | J86: Hyderabad | K86: Grocery | L86: P4591 | M86: Sunflower Oil | N86: Fortune | O86: 1 | P86: 4067 | Q86: 4600.77 | R86: 5 | S86: 4370.73 | T86: 533.77 | U86: Credit Card | V86: Cancelled | W86: 4 | X86: Hyderabad Hub | Y86: Dillon Walter | Z86: =TRIM(C86) -> David Price | AA86: =TRIM(I86) -> Telangana | AB86: =TRIM(J86) -> Hyderabad | AC86: =TRIM(K86) -> Grocery | AD86: =TRIM(M86) -> Sunflower Oil | AE86: =TRIM(N86) -> Fortune | AF86: =TRIM(X86) -> Hyderabad Hub | AG86: =TRIM(Y86) -> Dillon Walter
A87: ORD100085 | B87: CUST10085 | C87: Alicia Williams | D87: Male | E87: 30 | F87: Flipkart | G87: 45538 | H87: 45763 | J87: Hyderabad | K87: Electronics | L87: P4020 | M87: Galaxy S24 | N87: Samsung | O87: 1 | P87: 20204 | Q87: 25799.41 | R87: 20 | S87: 20639.53 | T87: 5595.41 | U87: COD | V87: In Transit | W87: 5 | X87: Hyderabad Hub | Y87: Charles Moore | Z87: =TRIM(C87) -> Alicia Williams | AA87: Telangana | AB87: =TRIM(J87) -> Hyderabad | AC87: =TRIM(K87) -> Electronics | AD87: =TRIM(M87) -> Galaxy S24 | AE87: =TRIM(N87) -> Samsung | AF87: =TRIM(X87) -> Hyderabad Hub | AG87: =TRIM(Y87) -> Charles Moore
A88: ORD100086 | B88: CUST10086 | C88: Scott Johnson | D88: Male | E88: 21 | F88: Amazon | G88: 45938 | H88: 45620 | I88: Maharashtra | J88: Mumbai | K88: Electronics | L88: P7653 | M88: Pressure Cooker | N88: Prestige | O88: 5 | P88: 2935 | Q88: 4246.66 | R88: 20 | S88: 16986.64 | T88: 6558.3 | U88: Credit Card | V88: Returned | W88: 1 | X88: Mumbai Hub | Y88: Scott Woodard | Z88: =TRIM(C88) -> Scott Johnson | AA88: =TRIM(I88) -> Maharashtra | AB88: =TRIM(J88) -> Mumbai | AC88: =TRIM(K88) -> Electronics | AD88: =TRIM(M88) -> Pressure Cooker | AE88: =TRIM(N88) -> Prestige | AF88: =TRIM(X88) -> Mumbai Hub | AG88: =TRIM(Y88) -> Scott Woodard
A89: ORD100087 | B89: CUST10087 | C89: Martha Hayes MD | D89: Male | E89: 55 | F89: Amazon | G89: 45733 | H89: 45692 | I89: Telangana | J89: Hyderabad | K89: Home | L89: P9025 | M89: Pressure Cooker | N89: Prestige | O89: 2 | P89: 11628 | Q89: 16635.4 | R89: 0 | S89: 33270.8 | T89: 10014.8 | U89: Credit Card | V89: Returned | W89: 2 | X89: Hyderabad Hub | Y89: Tonya Stark | Z89: =TRIM(C89) -> Martha Hayes MD | AA89: =TRIM(I89) -> Telangana | AB89: =TRIM(J89) -> Hyderabad | AC89: =TRIM(K89) -> Home | AD89: =TRIM(M89) -> Pressure Cooker | AE89: =TRIM(N89) -> Prestige | AF89: =TRIM(X89) -> Hyderabad Hub | AG89: =TRIM(Y89) -> Tonya Stark
A90: ORD100088 | B90: CUST10088 | C90: James Douglas | D90: Female | E90: 38 | F90: Amazon | G90: 45599 | H90: 46161 | I90: Delhi | J90: New Delhi | K90: Fashion | L90: P6023 | M90: Air Max Shoes | N90: Nike | O90: 2 | P90: 4071 | Q90: 6016.91 | R90: 10 | S90: 10830.44 | T90: 3891.82 | U90: Debit Card | V90: Returned | W90: 3 | X90: New Delhi Hub | Y90: Christine Horn | Z90: =TRIM(C90) -> James Douglas | AA90: =TRIM(I90) -> Delhi | AB90: =TRIM(J90) -> New Delhi | AC90: =TRIM(K90) -> Fashion | AD90: =TRIM(M90) -> Air Max Shoes | AE90: =TRIM(N90) -> Nike | AF90: =TRIM(X90) -> New Delhi Hub | AG90: =TRIM(Y90) -> Christine Horn
A91: ORD100089 | B91: CUST10089 | C91: Jeremy Ballard | D91: Male | E91: 47 | F91: Amazon | G91: 45860 | H91: 45764 | I91: Karnataka | J91: Bengaluru | K91: Fashion | L91: P5208 | M91: Air Max Shoes | N91: Nike | O91: 4 | P91: 542 | Q91: 720.88 | R91: 5 | S91: 2739.34 | T91: 715.52 | U91: UPI | V91: Cancelled | W91: 2 | X91: Bengaluru Hub | Y91: Julie Grimes | Z91: =TRIM(C91) -> Jeremy Ballard | AA91: =TRIM(I91) -> Karnataka | AB91: =TRIM(J91) -> Bengaluru | AC91: =TRIM(K91) -> Fashion | AD91: =TRIM(M91) -> Air Max Shoes | AE91: =TRIM(N91) -> Nike | AF91: =TRIM(X91) -> Bengaluru Hub | AG91: =TRIM(Y91) -> Julie Grimes
A92: ORD100090 | B92: CUST10090 | C92: Roger Sutton | D92: Male | E92: 27 | F92: Amazon | G92: 46004 | H92: 45830 | J92: Chennai | K92: Fashion | L92: P4867 | M92: Air Max Shoes | N92: Nike | O92: 2 | P92: 27409 | Q92: 32832.8 | R92: 10 | S92: 59099.04 | T92: 10847.6 | U92: Credit Card | V92: Returned | W92: 2 | X92: Chennai Hub | Y92: Dale Wood | Z92: =TRIM(C92) -> Roger Sutton | AA92: Tamil Nadu | AB92: =TRIM(J92) -> Chennai | AC92: =TRIM(K92) -> Fashion | AD92: =TRIM(M92) -> Air Max Shoes | AE92: =TRIM(N92) -> Nike | AF92: =TRIM(X92) -> Chennai Hub | AG92: =TRIM(Y92) -> Dale Wood
A93: ORD100091 | B93: CUST10091 | C93: Jessica Howard | D93: Female | E93: 59 | F93: Amazon | G93: 45832 | H93: 45820 | I93: Delhi | J93: New Delhi | K93: Beauty | L93: P6132 | M93: Face Wash | N93: Loreal | O93: 5 | P93: 15267 | Q93: 20602.59 | R93: 10 | S93: 92711.65 | T93: 26677.95 | U93: Debit Card | V93: In Transit | W93: 3 | X93: New Delhi Hub | Y93: Brianna Peterson | Z93: =TRIM(C93) -> Jessica Howard | AA93: =TRIM(I93) -> Delhi | AB93: =TRIM(J93) -> New Delhi | AC93: =TRIM(K93) -> Beauty | AD93: =TRIM(M93) -> Face Wash | AE93: =TRIM(N93) -> Loreal | AF93: =TRIM(X93) -> New Delhi Hub | AG93: =TRIM(Y93) -> Brianna Peterson
A94: ORD100092 | B94: CUST10092 | C94: Gabrielle Roth | D94: Male | E94: 32 | F94: Flipkart | G94: 45715 | H94: 45716 | I94: Delhi | J94: New Delhi | K94: Grocery | L94: P3129 | M94: Sunflower Oil | N94: Fortune | O94: 3 | P94: 23028 | Q94: 26051.42 | R94: 0 | S94: 78154.26 | T94: 9070.26 | U94: Credit Card | V94: Cancelled | W94: 1 | X94: New Delhi Hub | Y94: John Lewis | Z94: =TRIM(C94) -> Gabrielle Roth | AA94: =TRIM(I94) -> Delhi | AB94: =TRIM(J94) -> New Delhi | AC94: =TRIM(K94) -> Grocery | AD94: =TRIM(M94) -> Sunflower Oil | AE94: =TRIM(N94) -> Fortune | AF94: =TRIM(X94) -> New Delhi Hub | AG94: =TRIM(Y94) -> John Lewis
A95: ORD100093 | B95: CUST10093 | C95: Michael Riley | D95: Male | E95: 49 | F95: Amazon | G95: 45842 | H95: 46187 | I95: Karnataka | J95: Bengaluru | K95: Grocery | L95: P5747 | M95: Sunflower Oil | N95: Fortune | O95: 4 | P95: 9934 | Q95: 14830.92 | R95: 5 | S95: 56357.5 | T95: 19587.68 | U95: UPI | V95: Cancelled | W95: 4 | X95: Bengaluru Hub | Y95: Ronald Phillips | Z95: =TRIM(C95) -> Michael Riley | AA95: =TRIM(I95) -> Karnataka | AB95: =TRIM(J95) -> Bengaluru | AC95: =TRIM(K95) -> Grocery | AD95: =TRIM(M95) -> Sunflower Oil | AE95: =TRIM(N95) -> Fortune | AF95: =TRIM(X95) -> Bengaluru Hub | AG95: =TRIM(Y95) -> Ronald Phillips
A96: ORD100094 | B96: CUST10094 | C96: Ryan Stevens | D96: Female | E96: 36 | F96: Amazon | G96: 45748 | H96: 45653 | I96: Maharashtra | J96: Chennai | K96: Beauty | L96: P5748 | M96: Face Wash | N96: Loreal | O96: 3 | P96: 28202 | Q96: 33957.63 | R96: 20 | S96: 81498.31 | T96: 17266.89 | U96: Credit Card | V96: Returned | W96: 2 | X96: Chennai Hub | Y96: Carrie Hamilton | Z96: =TRIM(C96) -> Ryan Stevens | AA96: =TRIM(I96) -> Maharashtra | AB96: =TRIM(J96) -> Chennai | AC96: =TRIM(K96) -> Beauty | AD96: =TRIM(M96) -> Face Wash | AE96: =TRIM(N96) -> Loreal | AF96: =TRIM(X96) -> Chennai Hub | AG96: =TRIM(Y96) -> Carrie Hamilton
A97: ORD100095 | B97: CUST10095 | C97: Denise Johnston | D97: Male | E97: 38 | F97: Amazon | G97: 45788 | H97: 45646 | I97: Tamil Nadu | J97: Chennai | K97: Electronics | L97: P4934 | M97: Galaxy S24 | N97: Samsung | O97: 1 | P97: 11734 | Q97: 14545.73 | R97: 15 | S97: 12363.87 | T97: 2811.73 | U97: Credit Card | V97: In Transit | W97: 1 | X97: Chennai Hub | Y97: Melissa Clark | Z97: =TRIM(C97) -> Denise Johnston | AA97: =TRIM(I97) -> Tamil Nadu | AB97: =TRIM(J97) -> Chennai | AC97: =TRIM(K97) -> Electronics | AD97: =TRIM(M97) -> Galaxy S24 | AE97: =TRIM(N97) -> Samsung | AF97: =TRIM(X97) -> Chennai Hub | AG97: =TRIM(Y97) -> Melissa Clark
A98: ORD100096 | B98: CUST10096 | C98: Helen Davis | D98: Female | E98: 32 | F98: Amazon | G98: 45524 | H98: 45927 | I98: Maharashtra | J98: Pune | K98: Electronics | L98: P4337 | M98: Galaxy S24 | N98: Samsung | O98: 3 | P98: 24769 | Q98: 27491.34 | R98: 0 | S98: 82474.02 | T98: 8167.02 | U98: Credit Card | V98: Returned | W98: 5 | X98: Pune Hub | Y98: Raven Howell | Z98: =TRIM(C98) -> Helen Davis | AA98: =TRIM(I98) -> Maharashtra | AB98: =TRIM(J98) -> Pune | AC98: =TRIM(K98) -> Electronics | AD98: =TRIM(M98) -> Galaxy S24 | AE98: =TRIM(N98) -> Samsung | AF98: =TRIM(X98) -> Pune Hub | AG98: =TRIM(Y98) -> Raven Howell
A99: ORD100097 | B99: CUST10097 | C99: William Gonzales | D99: Male | E99: 32 | F99: Amazon | G99: 45504 | H99: 46069 | I99: Delhi | J99: New Delhi | K99: Beauty | L99: P2438 | M99: Face Wash | N99: Loreal | O99: 1 | P99: 2439 | Q99: 3175.54 | R99: 5 | S99: 3016.76 | T99: 736.54 | U99: Credit Card | V99: Returned | W99: 3 | X99: New Delhi Hub | Y99: Shannon Miller | Z99: =TRIM(C99) -> William Gonzales | AA99: =TRIM(I99) -> Delhi | AB99: =TRIM(J99) -> New Delhi | AC99: =TRIM(K99) -> Beauty | AD99: =TRIM(M99) -> Face Wash | AE99: =TRIM(N99) -> Loreal | AF99: =TRIM(X99) -> New Delhi Hub | AG99: =TRIM(Y99) -> Shannon Miller
A100: ORD100098 | B100: CUST10098 | C100: Thomas Stewart | D100: Female | E100: 50 | F100: Amazon | G100: 45898 | H100: 45843 | I100: Tamil Nadu | J100: Chennai | K100: Beauty | L100: P6405 | M100: Face Wash | N100: Loreal | O100: 5 | P100: 5246 | Q100: 7518.73 | R100: 10 | S100: 33834.28 | T100: 11363.65 | U100: Debit Card | V100: In Transit | W100: 3 | X100: Chennai Hub | Y100: Kylie May | Z100: =TRIM(C100) -> Thomas Stewart | AA100: =TRIM(I100) -> Tamil Nadu | AB100: =TRIM(J100) -> Chennai | AC100: =TRIM(K100) -> Beauty | AD100: =TRIM(M100) -> Face Wash | AE100: =TRIM(N100) -> Loreal | AF100: =TRIM(X100) -> Chennai Hub | AG100: =TRIM(Y100) -> Kylie May
A101: ORD100099 | B101: CUST10099 | C101: Katie Wood | D101: Male | E101: 45 | F101: Flipkart | G101: 45788 | H101: 46068 | I101: Telangana | J101: Hyderabad | K101: Electronics | L101: P7679 | M101: iPhone 15 | N101: Apple | O101: 4 | P101: 28717 | Q101: 39628.91 | R101: 10 | S101: 142664.08 | T101: 43647.64 | U101: UPI | V101: Cancelled | W101: 2 | X101: Hyderabad Hub | Y101: Connie Watson | Z101: =TRIM(C101) -> Katie Wood | AA101: =TRIM(I101) -> Telangana | AB101: =TRIM(J101) -> Hyderabad | AC101: =TRIM(K101) -> Electronics | AD101: =TRIM(M101) -> iPhone 15 | AE101: =TRIM(N101) -> Apple | AF101: =TRIM(X101) -> Hyderabad Hub | AG101: =TRIM(Y101) -> Connie Watson
A102: ORD100100 | B102: CUST10100 | C102: David Green | D102: Male | E102: 23 | F102: Amazon | G102: 45844 | H102: 45812 | I102: Delhi | J102: New Delhi | K102: Electronics | L102: P8090 | M102: Galaxy S24 | N102: Samsung | O102: 5 | P102: 16510 | Q102: 23961.54 | R102: 5 | S102: 113817.32 | T102: 37257.7 | U102: Debit Card | V102: In Transit | W102: 1 | X102: New Delhi Hub | Y102: Mikayla Jimenez | Z102: =TRIM(C102) -> David Green | AA102: =TRIM(I102) -> Delhi | AB102: =TRIM(J102) -> New Delhi | AC102: =TRIM(K102) -> Electronics | AD102: =TRIM(M102) -> Galaxy S24 | AE102: =TRIM(N102) -> Samsung | AF102: =TRIM(X102) -> New Delhi Hub | AG102: =TRIM(Y102) -> Mikayla Jimenez
A103: ORD100101 | B103: CUST10101 | C103: Tony Watson | D103: Female | E103: 35 | F103: Amazon | G103: 45767 | H103: 45646 | I103: Karnataka | J103: Bengaluru | K103: Electronics | L103: P9602 | M103: Galaxy S24 | N103: Samsung | O103: 2 | P103: 1296 | Q103: 1819.66 | R103: 0 | S103: 3639.32 | T103: 1047.32 | U103: Debit Card | V103: Returned | W103: 2 | X103: Bengaluru Hub | Y103: Matthew Obrien | Z103: =TRIM(C103) -> Tony Watson | AA103: =TRIM(I103) -> Karnataka | AB103: =TRIM(J103) -> Bengaluru | AC103: =TRIM(K103) -> Electronics | AD103: =TRIM(M103) -> Galaxy S24 | AE103: =TRIM(N103) -> Samsung | AF103: =TRIM(X103) -> Bengaluru Hub | AG103: =TRIM(Y103) -> Matthew Obrien
A104: ORD100102 | B104: CUST10102 | C104: Jordan Archer | D104: Female | E104: 26 | F104: Amazon | G104: 45964 | H104: 45871 | I104: Tamil Nadu | J104: Chennai | K104: Electronics | L104: P4662 | M104: iPhone 15 | N104: Apple | O104: 1 | P104: 23879 | Q104: 34067.44 | R104: 10 | S104: 30660.7 | T104: 10188.44 | U104: Credit Card | V104: Delivered | W104: 2 | X104: Chennai Hub | Y104: Joseph Chase | Z104: =TRIM(C104) -> Jordan Archer | AA104: =TRIM(I104) -> Tamil Nadu | AB104: =TRIM(J104) -> Chennai | AC104: =TRIM(K104) -> Electronics | AD104: =TRIM(M104) -> iPhone 15 | AE104: =TRIM(N104) -> Apple | AF104: =TRIM(X104) -> Chennai Hub | AG104: =TRIM(Y104) -> Joseph Chase
... A115: ORD100113 | B115: CUST10113 | C115: Anthony Rich | D115: Female | E115: 20 | F115: Amazon | G115: 46106 | H115: 45527 | I115: Telangana | J115: Hyderabad | K115: Grocery | L115: P7382 | M115: Sunflower Oil | N115: Fortune | O115: 2 | P115: 8191 | Q115: 10201.24 | R115: 20 | S115: 16321.98 | T115: 4020.48 | U115: Debit Card | V115: In Transit | W115: 2 | X115: Hyderabad Hub | Y115: Travis Mack | Z115: =TRIM(C115) -> Anthony Rich | AA115: =TRIM(I115) -> Telangana | AB115: =TRIM(J115) -> Hyderabad | AC115: =TRIM(K115) -> Grocery | AD115: =TRIM(M115) -> Sunflower Oil | AE115: =TRIM(N115) -> Fortune | AF115: =TRIM(X115) -> Hyderabad Hub | AG115: =TRIM(Y115) -> Travis Mack
A116: ORD100114 | B116: CUST10114 | C116: Kyle Hanson | D116: Male | E116: 18 | F116: Flipkart | G116: 45531 | H116: 45844 | I116: Telangana | J116: Hyderabad | K116: Home | L116: P9774 | N116: Prestige | O116: 4 | P116: 13874 | Q116: 15434.55 | R116: 10 | S116: 55564.38 | T116: 6242.2 | U116: Credit Card | V116: In Transit | W116: 3 | X116: Hyderabad Hub | Y116: Monica Frederick MD | Z116: =TRIM(C116) -> Kyle Hanson | AA116: =TRIM(I116) -> Telangana | AB116: =TRIM(J116) -> Hyderabad | AC116: =TRIM(K116) -> Home | AD116: Pressure Cooker | AE116: =TRIM(N116) -> Prestige | AF116: =TRIM(X116) -> Hyderabad Hub | AG116: =TRIM(Y116) -> Monica Frederick MD
A117: ORD100115 | B117: CUST10115 | C117: Mary Allen | D117: Female | E117: 30 | F117: Flipkart | G117: 46103 | H117: 45560 | I117: Karnataka | J117: Bengaluru | K117: Beauty | L117: P3988 | M117: Face Wash | N117: Loreal | O117: 3 | P117: 26179 | Q117: 32962.95 | R117: 10 | S117: 88999.96 | T117: 20351.85 | U117: COD | V117: Delivered | W117: 4 | X117: Bengaluru Hub | Y117: James Williams | Z117: =TRIM(C117) -> Mary Allen | AA117: =TRIM(I117) -> Karnataka | AB117: =TRIM(J117) -> Bengaluru | AC117: =TRIM(K117) -> Beauty | AD117: =TRIM(M117) -> Face Wash | AE117: =TRIM(N117) -> Loreal | AF117: =TRIM(X117) -> Bengaluru Hub | AG117: =TRIM(Y117) -> James Williams
A118: ORD100116 | B118: CUST10116 | C118: Cynthia Smith | D118: Male | E118: 52 | F118: Amazon | G118: 45800 | H118: 46167 | I118: Maharashtra | J118: Pune | K118: Electronics | L118: P5845 | M118: Galaxy S24 | N118: Samsung | O118: 5 | P118: 27891 | Q118: 41038.82 | R118: 10 | S118: 184674.69 | T118: 65739.1 | U118: COD | V118: In Transit | W118: 5 | X118: Pune Hub | Y118: Alfred Buchanan | Z118: =TRIM(C118) -> Cynthia Smith | AA118: =TRIM(I118) -> Maharashtra | AB118: =TRIM(J118) -> Pune | AC118: =TRIM(K118) -> Electronics | AD118: =TRIM(M118) -> Galaxy S24 | AE118: =TRIM(N118) -> Samsung | AF118: =TRIM(X118) -> Pune Hub | AG118: =TRIM(Y118) -> Alfred Buchanan
A119: ORD100117 | B119: CUST10117 | C119: Kimberly Gibson | D119: Female | E119: 26 | F119: Flipkart | G119: 45960 | H119: 45990 | I119: Tamil Nadu | J119: Chennai | K119: Fashion | L119: P3569 | M119: Air Max Shoes | N119: Nike | O119: 5 | P119: 12117 | Q119: 15843.51 | R119: 20 | S119: 63374.04 | T119: 18632.55 | U119: Debit Card | V119: In Transit | W119: 5 | X119: Chennai Hub | Y119: Craig Long | Z119: =TRIM(C119) -> Kimberly Gibson | AA119: =TRIM(I119) -> Tamil Nadu | AB119: =TRIM(J119) -> Chennai | AC119: =TRIM(K119) -> Fashion | AD119: =TRIM(M119) -> Air Max Shoes | AE119: =TRIM(N119) -> Nike | AF119: =TRIM(X119) -> Chennai Hub | AG119: =TRIM(Y119) -> Craig Long
A120: ORD100118 | B120: CUST10118 | C120: Peter Summers | D120: Male | E120: 29 | F120: Flipkart | G120: 45513 | H120: 46101 | I120: Delhi | J120: New Delhi | K120: Beauty | L120: P3134 | M120: Face Wash | N120: Loreal | O120: 1 | P120: 23706 | Q120: 29450.29 | R120: 0 | S120: 29450.29 | T120: 5744.29 | U120: Debit Card | V120: Returned | W120: 1 | X120: New Delhi Hub | Y120: Kelly Mosley | Z120: =TRIM(C120) -> Peter Summers | AA120: =TRIM(I120) -> Delhi | AB120: =TRIM(J120) -> New Delhi | AC120: =TRIM(K120) -> Beauty | AD120: =TRIM(M120) -> Face Wash | AE120: =TRIM(N120) -> Loreal | AF120: =TRIM(X120) -> New Delhi Hub | AG120: =TRIM(Y120) -> Kelly Mosley
A121: ORD100119 | B121: CUST10119 | C121: Kevin Snyder | D121: Male | E121: 48 | F121: Amazon | G121: 46038 | H121: 46077 | I121: Karnataka | J121: Bengaluru | K121: Beauty | L121: P8674 | M121: Face Wash | N121: Loreal | O121: 5 | P121: 28159 | Q121: 41918.15 | R121: 5 | S121: 199111.21 | T121: 68795.75 | U121: UPI | V121: In Transit | W121: 3 | X121: Bengaluru Hub | Y121: Vicki Brown | Z121: =TRIM(C121) -> Kevin Snyder | AA121: =TRIM(I121) -> Karnataka | AB121: =TRIM(J121) -> Bengaluru | AC121: =TRIM(K121) -> Beauty | AD121: =TRIM(M121) -> Face Wash | AE121: =TRIM(N121) -> Loreal | AF121: =TRIM(X121) -> Bengaluru Hub | AG121: =TRIM(Y121) -> Vicki Brown
A122: ORD100120 | B122: CUST10120 | C122: Michael Jensen | D122: Male | E122: 19 | F122: Flipkart | G122: 45722 | H122: 45827 | I122: Delhi | J122: New Delhi | K122: Home | L122: P9806 | M122: Pressure Cooker | N122: Prestige | O122: 2 | P122: 14880 | Q122: 22161.45 | R122: 5 | S122: 42106.75 | T122: 14562.9 | U122: UPI | V122: Returned | W122: 1 | X122: New Delhi Hub | Y122: Nicole Mccann | Z122: =TRIM(C122) -> Michael Jensen | AA122: =TRIM(I122) -> Delhi | AB122: =TRIM(J122) -> New Delhi | AC122: =TRIM(K122) -> Home | AD122: =TRIM(M122) -> Pressure Cooker | AE122: =TRIM(N122) -> Prestige | AF122: =TRIM(X122) -> New Delhi Hub | AG122: =TRIM(Y122) -> Nicole Mccann
A123: ORD100121 | B123: CUST10121 | C123: Kathryn Cox | D123: Female | E123: 19 | F123: Flipkart | G123: 45830 | H123: 45520 | I123: Karnataka | J123: Bengaluru | K123: Fashion | L123: P7952 | M123: Air Max Shoes | N123: Nike | O123: 1 | P123: 11729 | Q123: 17452.29 | R123: 10 | S123: 15707.06 | T123: 5723.29 | U123: COD | V123: Delivered | W123: 1 | X123: Bengaluru Hub | Y123: Steven Murray | Z123: =TRIM(C123) -> Kathryn Cox | AA123: =TRIM(I123) -> Karnataka | AB123: =TRIM(J123) -> Bengaluru | AC123: =TRIM(K123) -> Fashion | AD123: =TRIM(M123) -> Air Max Shoes | AE123: =TRIM(N123) -> Nike | AF123: =TRIM(X123) -> Bengaluru Hub | AG123: =TRIM(Y123) -> Steven Murray
A124: ORD100122 | B124: CUST10122 | C124: Andrew Holland | D124: Male | E124: 29 | F124: Flipkart | G124: 46069 | H124: 45514 | I124: Tamil Nadu | J124: Chennai | K124: Electronics | L124: P7156 | M124: iPhone 15 | N124: Apple | O124: 3 | P124: 25198 | Q124: 33188.73 | R124: 15 | S124: 84631.26 | T124: 23972.19 | U124: Credit Card | V124: Returned | W124: 4 | X124: Chennai Hub | Y124: Ryan Boyle | Z124: =TRIM(C124) -> Andrew Holland | AA124: =TRIM(I124) -> Tamil Nadu | AB124: =TRIM(J124) -> Chennai | AC124: =TRIM(K124) -> Electronics | AD124: =TRIM(M124) -> iPhone 15 | AE124: =TRIM(N124) -> Apple | AF124: =TRIM(X124) -> Chennai Hub | AG124: =TRIM(Y124) -> Ryan Boyle
A125: ORD100123 | B125: CUST10123 | C125: Emily Pope | D125: Male | E125: 23 | F125: Amazon | G125: 45903 | H125: 46044 | I125: Telangana | J125: Hyderabad | K125: Home | L125: P6362 | M125: Pressure Cooker | N125: Prestige | O125: 2 | P125: 23524 | Q125: 26090.42 | R125: 0 | S125: 52180.84 | T125: 5132.84 | U125: Credit Card | V125: Returned | W125: 3 | X125: Hyderabad Hub | Y125: Richard Castro | Z125: =TRIM(C125) -> Emily Pope | AA125: =TRIM(I125) -> Telangana | AB125: =TRIM(J125) -> Hyderabad | AC125: =TRIM(K125) -> Home | AD125: =TRIM(M125) -> Pressure Cooker | AE125: =TRIM(N125) -> Prestige | AF125: =TRIM(X125) -> Hyderabad Hub | AG125: =TRIM(Y125) -> Richard Castro
A126: ORD100124 | B126: CUST10124 | C126: Tyrone Mckay | D126: Female | E126: 22 | F126: Amazon | G126: 45948 | H126: 45553 | I126: Tamil Nadu | J126: Chennai | K126: Electronics | L126: P6110 | M126: iPhone 15 | N126: Apple | O126: 3 | P126: 19984 | Q126: 24049.15 | R126: 5 | S126: 68540.08 | T126: 12195.45 | U126: COD | V126: Cancelled | W126: 5 | X126: Chennai Hub | Y126: Roy Brown | Z126: =TRIM(C126) -> Tyrone Mckay | AA126: =TRIM(I126) -> Tamil Nadu | AB126: =TRIM(J126) -> Chennai | AC126: =TRIM(K126) -> Electronics | AD126: =TRIM(M126) -> iPhone 15 | AE126: =TRIM(N126) -> Apple | AF126: =TRIM(X126) -> Chennai Hub | AG126: =TRIM(Y126) -> Roy Brown
A127: ORD100125 | B127: CUST10125 | C127: Brandon Cooley | D127: Male | E127: 51 | F127: Flipkart | G127: 45559 | H127: 45884 | I127: Telangana | J127: Hyderabad | K127: Fashion | L127: P8028 | M127: Air Max Shoes | N127: Nike | O127: 3 | P127: 26019 | Q127: 37572.64 | R127: 20 | S127: 90174.34 | T127: 34660.92 | U127: COD | V127: Delivered | W127: 3 | X127: Hyderabad Hub | Y127: John Scott | Z127: =TRIM(C127) -> Brandon Cooley | AA127: =TRIM(I127) -> Telangana | AB127: =TRIM(J127) -> Hyderabad | AC127: =TRIM(K127) -> Fashion | AD127: =TRIM(M127) -> Air Max Shoes | AE127: =TRIM(N127) -> Nike | AF127: =TRIM(X127) -> Hyderabad Hub | AG127: =TRIM(Y127) -> John Scott
A128: ORD100126 | B128: CUST10126 | C128: James Kidd | D128: Female | E128: 55 | F128: Flipkart | G128: 45510 | H128: 45668 | I128: Maharashtra | J128: Mumbai | K128: Home | L128: P8736 | M128: Pressure Cooker | N128: Prestige | O128: 3 | P128: 29219 | Q128: 32815.98 | R128: 5 | S128: 93525.54 | T128: 10790.94 | U128: Debit Card | V128: Cancelled | W128: 5 | X128: Mumbai Hub | Y128: Kelsey Richardson | Z128: =TRIM(C128) -> James Kidd | AA128: =TRIM(I128) -> Maharashtra | AB128: =TRIM(J128) -> Mumbai | AC128: =TRIM(K128) -> Home | AD128: =TRIM(M128) -> Pressure Cooker | AE128: =TRIM(N128) -> Prestige | AF128: =TRIM(X128) -> Mumbai Hub | AG128: =TRIM(Y128) -> Kelsey Richardson
... A130: ORD100128 | B130: CUST10128 | C130: Chelsea Jones | D130: Female | E130: 25 | F130: Flipkart | G130: 45511 | H130: 45864 | I130: Maharashtra | J130: Mumbai | K130: Grocery | L130: P1082 | M130: Sunflower Oil | N130: Fortune | O130: 2 | P130: 10878 | Q130: 13744.18 | R130: 0 | S130: 27488.36 | T130: 5732.36 | U130: Credit Card | V130: Cancelled | W130: 4 | X130: Mumbai Hub | Y130: John Jones | Z130: =TRIM(C130) -> Chelsea Jones | AA130: =TRIM(I130) -> Maharashtra | AB130: =TRIM(J130) -> Mumbai | AC130: =TRIM(K130) -> Grocery | AD130: =TRIM(M130) -> Sunflower Oil | AE130: =TRIM(N130) -> Fortune | AF130: =TRIM(X130) -> Mumbai Hub | AG130: =TRIM(Y130) -> John Jones
A131: ORD100129 | B131: CUST10129 | C131: Mary Nelson | D131: Male | E131: 32 | F131: Amazon | G131: 45668 | H131: 46011 | I131: Delhi | J131: New Delhi | K131: Electronics | L131: P4486 | N131: Samsung | O131: 1 | P131: 5877 | Q131: 7439 | R131: 5 | S131: 7067.05 | T131: 1562 | U131: COD | V131: In Transit | W131: 2 | X131: New Delhi Hub | Y131: Jeffrey Hodges | Z131: =TRIM(C131) -> Mary Nelson | AA131: =TRIM(I131) -> Delhi | AB131: =TRIM(J131) -> New Delhi | AC131: =TRIM(K131) -> Electronics | AD131: Galaxy S24 | AE131: =TRIM(N131) -> Samsung | AF131: =TRIM(X131) -> New Delhi Hub | AG131: =TRIM(Y131) -> Jeffrey Hodges
A132: ORD100130 | B132: CUST10130 | C132: Cole Rodriguez | D132: Female | E132: 30 | F132: Amazon | G132: 46014 | H132: 45966 | I132: Tamil Nadu | J132: Chennai | K132: Grocery | L132: P7375 | M132: Sunflower Oil | N132: Fortune | O132: 5 | P132: 17429 | Q132: 21115.22 | R132: 20 | S132: 84460.88 | T132: 18431.1 | U132: Debit Card | V132: Cancelled | W132: 4 | X132: Chennai Hub | Y132: Richard Mason | Z132: =TRIM(C132) -> Cole Rodriguez | AA132: =TRIM(I132) -> Tamil Nadu | AB132: =TRIM(J132) -> Chennai | AC132: =TRIM(K132) -> Grocery | AD132: =TRIM(M132) -> Sunflower Oil | AE132: =TRIM(N132) -> Fortune | AF132: =TRIM(X132) -> Chennai Hub | AG132: =TRIM(Y132) -> Richard Mason
A133: ORD100131 | B133: CUST10131 | C133: Christopher May | D133: Male | E133: 42 | F133: Amazon | G133: 45876 | H133: 45568 | I133: Delhi | J133: New Delhi | K133: Electronics | L133: P6513 | M133: iPhone 15 | N133: Apple | O133: 5 | P133: 12576 | Q133: 13959.98 | R133: 15 | S133: 59329.91 | T133: 6919.9 | U133: COD | V133: Delivered | W133: 3 | X133: New Delhi Hub | Y133: Jennifer Hansen | Z133: =TRIM(C133) -> Christopher May | AA133: =TRIM(I133) -> Delhi | AB133: =TRIM(J133) -> New Delhi | AC133: =TRIM(K133) -> Electronics | AD133: =TRIM(M133) -> iPhone 15 | AE133: =TRIM(N133) -> Apple | AF133: =TRIM(X133) -> New Delhi Hub | AG133: =TRIM(Y133) -> Jennifer Hansen
A134: ORD100132 | B134: CUST10132 | C134: Melissa Juarez | D134: Male | E134: 49 | F134: Flipkart | G134: 46026 | H134: 45559 | I134: Maharashtra | J134: Pune | K134: Home | L134: P8884 | M134: Pressure Cooker | N134: Prestige | O134: 1 | P134: 6157 | Q134: 8892.67 | R134: 20 | S134: 7114.14 | T134: 2735.67 | U134: COD | V134: Cancelled | W134: 2 | X134: Pune Hub | Y134: Robert Castillo | Z134: =TRIM(C134) -> Melissa Juarez | AA134: =TRIM(I134) -> Maharashtra | AB134: =TRIM(J134) -> Pune | AC134: =TRIM(K134) -> Home | AD134: =TRIM(M134) -> Pressure Cooker | AE134: =TRIM(N134) -> Prestige | AF134: =TRIM(X134) -> Pune Hub | AG134: =TRIM(Y134) -> Robert Castillo
A135: ORD100133 | B135: CUST10133 | C135: Tina Mueller | D135: Male | E135: 50 | F135: Flipkart | G135: 45556 | H135: 45837 | I135: Maharashtra | J135: Mumbai | K135: Fashion | L135: P7369 | M135: Air Max Shoes | N135: Nike | O135: 1 | P135: 25544 | Q135: 36467.4 | R135: 0 | S135: 36467.4 | T135: 10923.4 | U135: Credit Card | V135: In Transit | W135: 4 | X135: Mumbai Hub | Y135: Cynthia Dawson | Z135: =TRIM(C135) -> Tina Mueller | AA135: =TRIM(I135) -> Maharashtra | AB135: =TRIM(J135) -> Mumbai | AC135: =TRIM(K135) -> Fashion | AD135: =TRIM(M135) -> Air Max Shoes | AE135: =TRIM(N135) -> Nike | AF135: =TRIM(X135) -> Mumbai Hub | AG135: =TRIM(Y135) -> Cynthia Dawson
A136: ORD100134 | B136: CUST10134 | C136: Douglas Caldwell | D136: Female | E136: 39 | F136: Flipkart | G136: 46096 | H136: 46112 | I136: Tamil Nadu | J136: Chennai | K136: Home | L136: P2656 | M136: Pressure Cooker | N136: Prestige | O136: 1 | P136: 22035 | Q136: 28460.75 | R136: 20 | S136: 22768.6 | T136: 6425.75 | U136: COD | V136: In Transit | W136: 3 | X136: Chennai Hub | Y136: Lisa Cox | Z136: =TRIM(C136) -> Douglas Caldwell | AA136: =TRIM(I136) -> Tamil Nadu | AB136: =TRIM(J136) -> Chennai | AC136: =TRIM(K136) -> Home | AD136: =TRIM(M136) -> Pressure Cooker | AE136: =TRIM(N136) -> Prestige | AF136: =TRIM(X136) -> Chennai Hub | AG136: =TRIM(Y136) -> Lisa Cox
A137: ORD100135 | B137: CUST10135 | C137: Corey Gomez | D137: Female | E137: 22 | F137: Flipkart | G137: 45742 | H137: 45670 | I137: Maharashtra | J137: Mumbai | K137: Beauty | L137: P9479 | M137: Face Wash | N137: Loreal | O137: 3 | P137: 14869 | Q137: 19124.89 | R137: 0 | S137: 57374.67 | T137: 12767.67 | U137: Credit Card | V137: Delivered | W137: 3 | X137: Mumbai Hub | Y137: Jeffrey Long | Z137: =TRIM(C137) -> Corey Gomez | AA137: =TRIM(I137) -> Maharashtra | AB137: =TRIM(J137) -> Mumbai | AC137: =TRIM(K137) -> Beauty | AD137: =TRIM(M137) -> Face Wash | AE137: =TRIM(N137) -> Loreal | AF137: =TRIM(X137) -> Mumbai Hub | AG137: =TRIM(Y137) -> Jeffrey Long
A138: ORD100136 | B138: CUST10136 | C138: Calvin Holt | D138: Female | E138: 60 | F138: Amazon | G138: 45723 | H138: 45658 | I138: Delhi | J138: New Delhi | K138: Beauty | L138: P1722 | M138: Face Wash | N138: Loreal | O138: 3 | P138: 6839 | Q138: 9169.26 | R138: 20 | S138: 22006.22 | T138: 6990.78 | U138: Debit Card | V138: Cancelled | W138: 2 | X138: New Delhi Hub | Y138: Catherine Sparks | Z138: =TRIM(C138) -> Calvin Holt | AA138: =TRIM(I138) -> Delhi | AB138: =TRIM(J138) -> New Delhi | AC138: =TRIM(K138) -> Beauty | AD138: =TRIM(M138) -> Face Wash | AE138: =TRIM(N138) -> Loreal | AF138: =TRIM(X138) -> New Delhi Hub | AG138: =TRIM(Y138) -> Catherine Sparks
A139: ORD100137 | B139: CUST10137 | C139: Linda Adkins | D139: Male | E139: 33 | F139: Amazon | G139: 46155 | H139: 45576 | I139: Tamil Nadu | J139: Chennai | K139: Beauty | L139: P4859 | M139: Face Wash | N139: Loreal | O139: 4 | P139: 15832 | Q139: 19711.64 | R139: 20 | S139: 63077.25 | T139: 15518.56 | U139: UPI | V139: Returned | W139: 1 | X139: Chennai Hub | Y139: George Morales | Z139: =TRIM(C139) -> Linda Adkins | AA139: =TRIM(I139) -> Tamil Nadu | AB139: =TRIM(J139) -> Chennai | AC139: =TRIM(K139) -> Beauty | AD139: =TRIM(M139) -> Face Wash | AE139: =TRIM(N139) -> Loreal | AF139: =TRIM(X139) -> Chennai Hub | AG139: =TRIM(Y139) -> George Morales
A140: ORD100138 | B140: CUST10138 | C140: Jose Brown | D140: Female | E140: 53 | F140: Amazon | G140: 45494 | H140: 45573 | I140: Delhi | J140: New Delhi | K140: Beauty | L140: P4983 | M140: Face Wash | N140: Loreal | O140: 4 | P140: 27508 | Q140: 40398.1 | R140: 10 | S140: 145433.16 | T140: 51560.4 | U140: COD | V140: Returned | W140: 2 | X140: New Delhi Hub | Y140: Michael Harvey | Z140: =TRIM(C140) -> Jose Brown | AA140: =TRIM(I140) -> Delhi | AB140: =TRIM(J140) -> New Delhi | AC140: =TRIM(K140) -> Beauty | AD140: =TRIM(M140) -> Face Wash | AE140: =TRIM(N140) -> Loreal | AF140: =TRIM(X140) -> New Delhi Hub | AG140: =TRIM(Y140) -> Michael Harvey
A141: ORD100139 | B141: CUST10139 | C141: Robert Velasquez DDS | D141: Female | E141: 60 | F141: Flipkart | G141: 45855 | H141: 45699 | I141: Delhi | J141: New Delhi | K141: Electronics | L141: P8232 | M141: iPhone 15 | N141: Apple | O141: 3 | P141: 25438 | Q141: 36129.31 | R141: 0 | S141: 108387.93 | T141: 32073.93 | U141: UPI | V141: Returned | W141: 4 | X141: New Delhi Hub | Y141: Andrea Frazier | Z141: =TRIM(C141) -> Robert Velasquez DDS | AA141: =TRIM(I141) -> Delhi | AB141: =TRIM(J141) -> New Delhi | AC141: =TRIM(K141) -> Electronics | AD141: =TRIM(M141) -> iPhone 15 | AE141: =TRIM(N141) -> Apple | AF141: =TRIM(X141) -> New Delhi Hub | AG141: =TRIM(Y141) -> Andrea Frazier
A142: ORD100140 | B142: CUST10140 | C142: Tracy Carroll | D142: Female | E142: 43 | F142: Flipkart | G142: 45673 | H142: 46185 | I142: Maharashtra | J142: Mumbai | K142: Home | L142: P5730 | M142: Pressure Cooker | N142: Prestige | O142: 5 | P142: 12769 | Q142: 15971.95 | R142: 5 | S142: 75866.76 | T142: 16014.75 | U142: UPI | V142: Cancelled | W142: 2 | X142: Mumbai Hub | Y142: Erik Smith | Z142: =TRIM(C142) -> Tracy Carroll | AA142: =TRIM(I142) -> Maharashtra | AB142: =TRIM(J142) -> Mumbai | AC142: =TRIM(K142) -> Home | AD142: =TRIM(M142) -> Pressure Cooker | AE142: =TRIM(N142) -> Prestige | AF142: =TRIM(X142) -> Mumbai Hub | AG142: =TRIM(Y142) -> Erik Smith
A143: ORD100141 | B143: CUST10141 | C143: Karen Nelson | D143: Male | E143: 26 | F143: Flipkart | G143: 45828 | H143: 46135 | I143: Telangana | J143: Hyderabad | K143: Home | L143: P6061 | M143: Pressure Cooker | N143: Prestige | O143: 4 | P143: 13441 | Q143: 16025 | R143: 5 | S143: 60895 | T143: 10336 | U143: Debit Card | V143: In Transit | W143: 3 | X143: Hyderabad Hub | Y143: Mario Tran | Z143: =TRIM(C143) -> Karen Nelson | AA143: =TRIM(I143) -> Telangana | AB143: =TRIM(J143) -> Hyderabad | AC143: =TRIM(K143) -> Home | AD143: =TRIM(M143) -> Pressure Cooker | AE143: =TRIM(N143) -> Prestige | AF143: =TRIM(X143) -> Hyderabad Hub | AG143: =TRIM(Y143) -> Mario Tran
... A189: ORD100187 | B189: CUST10187 | C189: Shannon Wilson | D189: Female | E189: 40 | F189: Amazon | G189: 45936 | H189: 46069 | I189: Delhi | J189: New Delhi | K189: Electronics | L189: P4461 | M189: Galaxy S24 | N189: Samsung | O189: 5 | P189: 5245 | Q189: 6214.92 | R189: 20 | S189: 24859.68 | T189: 4849.6 | U189: Debit Card | V189: In Transit | W189: 5 | X189: New Delhi Hub | Y189: Ricky Richard | Z189: =TRIM(C189) -> Shannon Wilson | AA189: =TRIM(I189) -> Delhi | AB189: =TRIM(J189) -> New Delhi | AC189: =TRIM(K189) -> Electronics | AD189: =TRIM(M189) -> Galaxy S24 | AE189: =TRIM(N189) -> Samsung | AF189: =TRIM(X189) -> New Delhi Hub | AG189: =TRIM(Y189) -> Ricky Richard
A190: ORD100188 | B190: CUST10188 | C190: Garrett Robinson | D190: Female | E190: 52 | F190: Flipkart | G190: 45875 | H190: 46018 | I190: Maharashtra | J190: Chennai | K190: Home | L190: P1324 | M190: Pressure Cooker | N190: Prestige | O190: 4 | P190: 25218 | Q190: 30756.26 | R190: 5 | S190: 116873.79 | T190: 22153.04 | U190: Debit Card | V190: Cancelled | W190: 5 | X190: Chennai Hub | Y190: Michael Castaneda | Z190: =TRIM(C190) -> Garrett Robinson | AA190: Tamil Nadu | AB190: =TRIM(J190) -> Chennai | AC190: =TRIM(K190) -> Home | AD190: =TRIM(M190) -> Pressure Cooker | AE190: =TRIM(N190) -> Prestige | AF190: =TRIM(X190) -> Chennai Hub | AG190: =TRIM(Y190) -> Michael Castaneda
A191: ORD100189 | B191: CUST10189 | C191: Sarah Grant | D191: Male | E191: 48 | F191: Flipkart | G191: 45931 | H191: 46101 | I191: Telangana | J191: Hyderabad | K191: Electronics | L191: P8516 | M191: Galaxy S24 | N191: Samsung | O191: 2 | P191: 13915 | Q191: 19774.13 | R191: 5 | S191: 37570.85 | T191: 11718.26 | U191: Credit Card | V191: Returned | W191: 1 | X191: Hyderabad Hub | Y191: Tina Barber | Z191: =TRIM(C191) -> Sarah Grant | AA191: =TRIM(I191) -> Telangana | AB191: =TRIM(J191) -> Hyderabad | AC191: =TRIM(K191) -> Electronics | AD191: =TRIM(M191) -> Galaxy S24 | AE191: =TRIM(N191) -> Samsung | AF191: =TRIM(X191) -> Hyderabad Hub | AG191: =TRIM(Y191) -> Tina Barber
A192: ORD100190 | B192: CUST10190 | C192: Bailey Gomez | D192: Female | E192: 34 | F192: Amazon | G192: 46075 | H192: 45914 | I192: Telangana | J192: Hyderabad | K192: Electronics | L192: P1987 | M192: Galaxy S24 | N192: Samsung | O192: 5 | P192: 21357 | Q192: 25498.7 | R192: 15 | S192: 108369.47 | T192: 20708.5 | U192: Credit Card | V192: Delivered | W192: 1 | X192: Hyderabad Hub | Y192: Corey Martinez | Z192: =TRIM(C192) -> Bailey Gomez | AA192: =TRIM(I192) -> Telangana | AB192: =TRIM(J192) -> Hyderabad | AC192: =TRIM(K192) -> Electronics | AD192: =TRIM(M192) -> Galaxy S24 | AE192: =TRIM(N192) -> Samsung | AF192: =TRIM(X192) -> Hyderabad Hub | AG192: =TRIM(Y192) -> Corey Martinez
A193: ORD100191 | B193: CUST10191 | C193: Mason Carr | D193: Female | E193: 56 | F193: Amazon | G193: 45789 | H193: 45611 | I193: Karnataka | J193: Bengaluru | K193: Home | L193: P2556 | N193: Prestige | O193: 3 | P193: 20683 | Q193: 24955.6 | R193: 20 | S193: 59893.44 | T193: 12817.8 | U193: Credit Card | V193: Cancelled | W193: 4 | X193: Bengaluru Hub | Y193: Teresa Church | Z193: =TRIM(C193) -> Mason Carr | AA193: =TRIM(I193) -> Karnataka | AB193: =TRIM(J193) -> Bengaluru | AC193: =TRIM(K193) -> Home | AD193: Pressure Cooker | AE193: =TRIM(N193) -> Prestige | AF193: =TRIM(X193) -> Bengaluru Hub | AG193: =TRIM(Y193) -> Teresa Church
A194: ORD100192 | B194: CUST10192 | C194: Robin Bell | D194: Female | E194: 60 | F194: Amazon | G194: 45505 | H194: 45557 | I194: Telangana | J194: Hyderabad | K194: Grocery | L194: P1038 | M194: Sunflower Oil | N194: Fortune | O194: 5 | P194: 2520 | Q194: 3443.72 | R194: 20 | S194: 13774.88 | T194: 4618.6 | U194: Credit Card | V194: In Transit | W194: 4 | X194: Hyderabad Hub | Y194: Jeremy Brown | Z194: =TRIM(C194) -> Robin Bell | AA194: =TRIM(I194) -> Telangana | AB194: =TRIM(J194) -> Hyderabad | AC194: =TRIM(K194) -> Grocery | AD194: =TRIM(M194) -> Sunflower Oil | AE194: =TRIM(N194) -> Fortune | AF194: =TRIM(X194) -> Hyderabad Hub | AG194: =TRIM(Y194) -> Jeremy Brown
A195: ORD100193 | B195: CUST10193 | C195: Eric Wolfe | D195: Male | E195: 27 | F195: Flipkart | G195: 45900 | H195: 45632 | I195: Delhi | J195: New Delhi | K195: Electronics | L195: P4217 | M195: iPhone 15 | N195: Apple | O195: 1 | P195: 17773 | Q195: 26292.85 | R195: 10 | S195: 23663.56 | T195: 8519.85 | U195: UPI | V195: Returned | W195: 2 | X195: New Delhi Hub | Y195: Jane Baker | Z195: =TRIM(C195) -> Eric Wolfe | AA195: =TRIM(I195) -> Delhi | AB195: =TRIM(J195) -> New Delhi | AC195: =TRIM(K195) -> Electronics | AD195: =TRIM(M195) -> iPhone 15 | AE195: =TRIM(N195) -> Apple | AF195: =TRIM(X195) -> New Delhi Hub | AG195: =TRIM(Y195) -> Jane Baker
A196: ORD100194 | B196: CUST10194 | C196: Elizabeth King | D196: Female | E196: 31 | F196: Amazon | G196: 45762 | H196: 45567 | I196: Delhi | J196: New Delhi | K196: Electronics | L196: P2324 | M196: Galaxy S24 | N196: Samsung | O196: 5 | P196: 16730 | Q196: 23975.37 | R196: 15 | S196: 101895.32 | T196: 36226.85 | U196: COD | V196: Delivered | W196: 3 | X196: New Delhi Hub | Y196: Wendy Shaw | Z196: =TRIM(C196) -> Elizabeth King | AA196: =TRIM(I196) -> Delhi | AB196: =TRIM(J196) -> New Delhi | AC196: =TRIM(K196) -> Electronics | AD196: =TRIM(M196) -> Galaxy S24 | AE196: =TRIM(N196) -> Samsung | AF196: =TRIM(X196) -> New Delhi Hub | AG196: =TRIM(Y196) -> Wendy Shaw
A197: ORD100195 | B197: CUST10195 | C197: Allen Schwartz | D197: Male | E197: 45 | F197: Amazon | G197: 45693 | H197: 45839 | I197: Maharashtra | J197: Pune | K197: Fashion | L197: P5750 | M197: Air Max Shoes | N197: Nike | O197: 5 | P197: 9307 | Q197: 10452.01 | R197: 15 | S197: 44421.04 | T197: 5725.05 | U197: COD | V197: Cancelled | W197: 5 | X197: Pune Hub | Y197: Cody Kennedy | Z197: =TRIM(C197) -> Allen Schwartz | AA197: =TRIM(I197) -> Maharashtra | AB197: =TRIM(J197) -> Pune | AC197: =TRIM(K197) -> Fashion | AD197: =TRIM(M197) -> Air Max Shoes | AE197: =TRIM(N197) -> Nike | AF197: =TRIM(X197) -> Pune Hub | AG197: =TRIM(Y197) -> Cody Kennedy
A198: ORD100196 | B198: CUST10196 | C198: Christine Richardson | D198: Male | E198: 34 | F198: Flipkart | G198: 45859 | H198: 45913 | I198: Telangana | J198: Hyderabad | K198: Electronics | L198: P2021 | M198: Galaxy S24 | N198: Samsung | O198: 5 | P198: 24172 | Q198: 36081.84 | R198: 15 | S198: 153347.82 | T198: 59549.2 | U198: COD | V198: Cancelled | W198: 5 | X198: Hyderabad Hub | Y198: Evan Lopez | Z198: =TRIM(C198) -> Christine Richardson | AA198: =TRIM(I198) -> Telangana | AB198: =TRIM(J198) -> Hyderabad | AC198: =TRIM(K198) -> Electronics | AD198: =TRIM(M198) -> Galaxy S24 | AE198: =TRIM(N198) -> Samsung | AF198: =TRIM(X198) -> Hyderabad Hub | AG198: =TRIM(Y198) -> Evan Lopez
A199: ORD100197 | B199: CUST10197 | C199: Dustin Carr | D199: Male | E199: 34 | F199: Amazon | G199: 45998 | H199: 45537 | I199: Telangana | J199: Hyderabad | K199: Electronics | L199: P9182 | M199: Galaxy S24 | N199: Samsung | O199: 1 | P199: 12382 | Q199: 13964.52 | R199: 0 | S199: 13964.52 | T199: 1582.52 | U199: COD | V199: Returned | W199: 4 | X199: Hyderabad Hub | Y199: Melissa Sosa | Z199: =TRIM(C199) -> Dustin Carr | AA199: =TRIM(I199) -> Telangana | AB199: =TRIM(J199) -> Hyderabad | AC199: =TRIM(K199) -> Electronics | AD199: =TRIM(M199) -> Galaxy S24 | AE199: =TRIM(N199) -> Samsung | AF199: =TRIM(X199) -> Hyderabad Hub | AG199: =TRIM(Y199) -> Melissa Sosa
A200: ORD100198 | B200: CUST10198 | C200: Michele Murphy | D200: Male | E200: 60 | F200: Amazon | G200: 45997 | H200: 46119 | I200: Maharashtra | J200: Mumbai | K200: Home | L200: P3490 | M200: Pressure Cooker | N200: Prestige | O200: 3 | P200: 25287 | Q200: 30904.03 | R200: 10 | S200: 83440.88 | T200: 16851.09 | U200: Debit Card | V200: Delivered | W200: 3 | X200: Mumbai Hub | Y200: William Reyes | Z200: =TRIM(C200) -> Michele Murphy | AA200: =TRIM(I200) -> Maharashtra | AB200: =TRIM(J200) -> Mumbai | AC200: =TRIM(K200) -> Home | AD200: =TRIM(M200) -> Pressure Cooker | AE200: =TRIM(N200) -> Prestige | AF200: =TRIM(X200) -> Mumbai Hub | AG200: =TRIM(Y200) -> William Reyes
A201: ORD100199 | B201: CUST10199 | C201: Audrey Crawford | D201: Male | E201: 24 | F201: Flipkart | G201: 45655 | H201: 46049 | I201: Telangana | J201: Hyderabad | K201: Electronics | L201: P4986 | M201: iPhone 15 | N201: Apple | O201: 4 | P201: 4042 | Q201: 5903.5 | R201: 0 | S201: 23614 | T201: 7446 | U201: COD | V201: Returned | W201: 5 | X201: Hyderabad Hub | Y201: David White | Z201: =TRIM(C201) -> Audrey Crawford | AA201: =TRIM(I201) -> Telangana | AB201: =TRIM(J201) -> Hyderabad | AC201: =TRIM(K201) -> Electronics | AD201: =TRIM(M201) -> iPhone 15 | AE201: =TRIM(N201) -> Apple | AF201: =TRIM(X201) -> Hyderabad Hub | AG201: =TRIM(Y201) -> David White
...

Sheet Data_Quality_Report
A1: Issue | B1: Before | C1: After
A2: Duplicate Records | B2: 210 | C2: 0
A3: Missing Values | B3: =COUNTBLANK(Sales_Analysis.xlsx!A1:Y5251) -> 359 | C3: 0
A4: Invalid State Names | B4: 100 | C4: 0
A5: Invalid Categories | B5: 100 | C5: 0
A6: Blank Product Names | B6: 120 | C6: 0

Sheet Data_Profiling
A1: Metric | B1: Value
A2: Total Records | B2: =ROWS(Sales_Analysis.xlsx!S2:Y5251) -> 5250
A3: Total Columns | B3: =COLUMNS(Sales_Analysis.xlsx!A1:Y1) -> 25
A4: Duplicate Records | B4: 210
A5: Missing Values | B5: =COUNTBLANK(Sales_Analysis.xlsx!A1:Y5251) -> 359
A6: Unique States | B6: =COUNT(_xlfn.UNIQUE(Cleaned_Data!AA2:AA5040)) -> 0
A7: Unique Categories | B7: =COUNT(_xlfn.UNIQUE(Cleaned_Data!AC2:AC5040)) -> 0
A8: Date Range | B8: =MAX(Cleaned_Data!G2:H5040)-MIN(Cleaned_Data!G2:H5040) -> 730
A11: =MIN(Cleaned_Data!G2:H5040) -> 45468 | B11: minimum date
A12: =MAX(Cleaned_Data!G2:H5040) -> 46198 | B12: maximum date

Sheet KPI_Summary
A1: A | B1: B
A2: KPI | B2: Value
A3: Total Sales | B3: =SUM(Cleaned_Data!S2:S5040) -> 2.6642113e+08
A4: Total Profit | B4: =SUM(Cleaned_Data!T2:T5040) -> 68063308
A5: Total Orders | B5: =COUNTA(Cleaned_Data!A2:A5040) -> 5039
A6: Total Quantity | B6: =SUM(Cleaned_Data!O2:O5040) -> 15223
A7: Average Rating | B7: =AVERAGE(Cleaned_Data!W2:W5040) -> 3.0075412
A8: Average Order Value | B8: =B3/B5 -> 52871.826

Sheet Pivot_Tables
A1: Row Labels | B1: Sum of Sales | F1: Row Labels | G1: Sum of Sales
A2: Amazon | B2: 1.3521612e+08 | F2: Delhi | G2: 50618172
A3: Flipkart | B3: 1.3120501e+08 | F3: Karnataka | G3: 51228078
A4: Grand Total | B4: 2.6642113e+08 | F4: Maharashtra | G4: 59647790
F5: Tamil Nadu | G5: 54112931
F6: Telangana | G6: 50814161
F7: Grand Total | G7: 2.6642113e+08
A20: Row Labels | B20: Sum of Sales | F20: Row Labels | G20: Sum of Sales
A21: Beauty | B21: 43006179 | F21: Jan | G21: 25599083
A22: Electronics | B22: 92570302 | F22: Feb | G22: 18973339
A23: Fashion | B23: 43061382 | F23: Mar | G23: 21618413
A24: Grocery | B24: 43849090 | F24: Apr | G24: 22460524
A25: Home | B25: 43934178 | F25: May | G25: 22281358
A26: Grand Total | B26: 2.6642113e+08 | F26: Jun | G26: 21969322
F27: Jul | G27: 22247075
F28: Aug | G28: 22082090
F29: Sep | G29: 20131984
F30: Oct | G30: 20580217
F31: Nov | G31: 22408764
F32: Dec | G32: 26068962
F33: Grand Total | G33: 2.6642113e+08
A40: Row Labels | B40: Sum of Sales | F40: Row Labels | G40: Sum of Sales
A41: Apple | B41: 43010153 | F41: COD | G41: 67396019
A42: Fortune | B42: 44613246 | F42: Credit Card | G42: 72141526
A43: Loreal | B43: 44269538 | F43: Debit Card | G43: 63881253
A44: Nike | B44: 43745164 | F44: UPI | G44: 63002333
A45: Prestige | B45: 44910669 | F45: Grand Total | G45: 2.6642113e+08
A46: Samsung | B46: 45872362
A47: Grand Total | B47: 2.6642113e+08
A60: Row Labels | B60: Count of Order_ID
A61: Cancelled | B61: 1293
A62: Delivered | B62: 1217
A63: In Transit | B63: 1262
A64: Returned | B64: 1267
A65: Grand Total | B65: 5039

Sheet Dashboard_Excel
